{"name":"Dunhill 1907 Toro","url":"https://www.noblego.de/dunhill-1907-toro/","brand":"Dunhill","series":"1907","details":{"Fazit":"Ein Genuss auf ganzer Linie: die Dunhill 1907 Toro im Box-pressed Format. Optimal ergänzt wird der Smoke mit einem Cappuccino oder einem fassgereiften Rum wie dem \u003ca title=\"Hier geht's zum B13 Rum von Bentley\" href=\"/b13-rum-barbados/\"\u003eBentley B13\u003c/a\u003e.","Genuss":"Nach wie vor zeichnen sich Zigarren der Marke Dunhill durch die Verwendung hochwertiger Tabake und deren perfekte Verarbeitung aus. Der Blend der Dunhill 1907 Toro besteht aus einer brasilianischen und dominikanischen Einlage, einem dominikanischen Umblatt und einem Olancho San Augustin Deckblatt aus Honduras. Im Gegensatz zu den anderen Formaten der Serie erscheint die Toro box-pressed, d.h. in fast rechteckiger, durch Kistenpressung entstandene Formgebung. Ihr mittelstarker Charakter sagt sowohl Einsteigern als auch erfahrenen Raucher zu. Aromatisch bewegt sich der 152 mm lange und 21,3 mm dicke Longfiller zwischen Noten von Holz, Karamell, Schokolade, etwas Erde und Pfeffer und gibt einen schön cremigen Rauch. Perfekter Zug und Abbrand sind fast schon selbstverständlich.","Hintergrund":"Anlässlich des 100-jährigen Jubiläums der Marke Dunhill kamen die Dunhill 1907 auf den Markt. Neben der Dominikanischen Republik ist Nicaragua eine weitere Produktionsstätte für Zigarren der Marke. Dort wird beispielsweise die \u003ca title=\"Hier geht's zu den Dunhill Signed Range Zigarren\" href=\"/dunhill-signed-range/\"\u003eDunhill Signed Range Serie\u003c/a\u003e produziert."},"diameter_mm":21.3,"ring":54,"length_mm":152,"length_inch":0,"format":"Toro","manufactureOrigin":"Dominikanische Republik","construction":"Longfiller","isBoxpressed":true,"wrapperOrigin":["Honduras"],"WrapperTobaccoVariety":"Olancho San Augustin","fillerOrigin":["Brasilien","Dominikanische Republik"],"binderOrigin":["Dominikanische Republik"],"aromaProfileManufacturer":["Cremig","Holz","Karamell","Röstaromen","Schokolade"],"strength":"Medium","flavourStrength":"Medium-aromatisch","smokingDuration":"45 bis 90 Min","price":7.6}
