{"name":"Alejandro Lopez Dominicana Maduro Gordo","url":"https://www.noblego.de/alejandro-lopez-dominicana-maduro-gordo/","brand":"Alejandro Lopez","series":"","details":{"Fazit":"Von der Alejandro Lopez Dominicana Maduro Gordo werden Sie schnell überzeugt sein. Unschlagbar günstig und lecker versüßt sie Ihnen den entspannten Genussalltag.","Genuss":"Eine günstige Sandwichfiller Zigarre wie die Alejandro Lopez Dominicana Maduro Gordo schenkt ihrem Genießer im Alltag zu jeder Gelegenheit entspannten Genuss. Ihre sanft-milde Auslegung macht sie zudem zu einem sehr angenehmen und unaufdringlichen Smoke, welcher über das große Ringmaß von 58 jede Menge cremigen Rauch entwickelt. Geschmacklich tendiert die Puro aus der Dominikanischen Republik zu vordergründig erdigen, holzigen und nussigen Noten, von einer ganz leichten Pfeffernote umspielt. Dazu kommt die typische Madurosüße, die diesen delikaten Smoke herrlich abrundet. Abbrand und Zug sind bei den gut gearbeiteten Bundle Zigarren nur ganz selten zu beanstanden.","Hintergrund":"Die Kreationen von Alejandro Lopez sind besonders beliebt bei Freunden des milden Zigarrengenusses. In der dominikanischen Manufaktur versteht man es besonders gut leichte Blends zu entwickeln, die mit einer für diesen Stärkegrad eher untypisch prägnanten Aromatik aufwarten können."},"diameter_mm":23,"ring":58,"length_mm":127,"length_inch":0,"format":"Gordo","manufactureOrigin":"Dominikanische Republik","construction":"Sandwichfiller","isBoxpressed":false,"wrapperOrigin":["Dominikanische Republik"],"fillerOrigin":["Dominikanische Republik"],"binderOrigin":["Dominikanische Republik"],"wrapperType":"Maduro","aromaProfileManufacturer":["Cremig","Erdig","Holz","Nuss","Pfeffer","Süß"],"strength":"Mild","flavourStrength":"Medium-aromatisch","smokingDuration":"45 bis 90 Min","price":2.9}
