{"name":"Joya de Nicaragua Antaño CT Toro","url":"https://www.noblego.de/joya-de-nicaragua-antano-ct-toro-zigarren/","brand":"Joya de Nicaragua","series":"Joya de Nicaragua Antaño CT","details":{"Genussverlauf":"Bis auf das hellbraune und seidig wirkende Connecticut Deckblatt aus Ecuador stammen alle Tabake der Joya de Nicaragua Antaño CT Toro aus Nicaragua. Gut 70 bis 80 Minuten verbringt man mit der sehr gut verarbeiteten Longfiller Zigarre. Gleich zu Beginn verströmt sie einen herrlich cremigen und dichten Rauch, der in den ersten Zügen einige Pfeffertöne sowie holzig-nussige Aromen parat hält. Der Pfeffer tritt alsbald in den Hintergrund und zeigt sich im weiteren Rauchverlauf eher noch auf subtiler Ebene. Im zweiten Rauchdrittel entwickelt der fein-würzige Smoke eine salzige Komponente, die wunderbar mit einer ebenfalls aufkommenden Karamellsüße korreliert. Das letzte Drittel wird bestimmt von vollmundigen und klaren Kaffee-, Erd- und Fruchtnoten. Unsere Probe-Exemplare zeigten in Sachen Zug und Abbrand so gut wie keinerlei Schwächen.","Resümee":"Eine sehr gut gelungene Zigarre aus Nicaragua! Die Joya de Nicaragua Antaño CT Toro wird sicher zahlreiche Liebhaber finden. Wunderbar cremig und abwechslungsreich im Geschmack. So etwas genießt man einfach gern!"},"diameter_mm":19.8,"ring":50,"length_mm":152,"length_inch":0,"format":"Toro","manufactureOrigin":"Nicaragua","construction":"Longfiller","isBoxpressed":false,"wrapperOrigin":["Ecuador"],"fillerOrigin":["Nicaragua"],"binderOrigin":["Nicaragua"],"binderProperty":"Connecticut Shade","aromaProfileManufacturer":["Cremig","Erdig","Fruchtig","Holz","Kaffee","Karamell","Nuss","Pfeffer","Salzig","Süß"],"strength":"Medium","smokingDuration":"45 bis 90 Min","price":9}
