{"name":"cenicero Limited Edition VI Robusto Gordo","url":"https://www.noblego.de/cenicero-limited-edition-vi-robusto-gordo/","brand":"Cenicero","series":"NICA","details":{"Fazit":"Die cenicero Limited Edition VI Robusto Gordo ist für gestandene Aficionados gedacht, welche kräftigen Zigarrengenuss mit dunklen Aromen und prägnanter Würze bevorzugen. Eine preisgünstige Bundle Zigarre, die jedoch wahren Premiumgenuss zu vermitteln weiß.","Genuss":"Ein dunkelbraunes und ölig schimmerndes Broadleaf Deckblatt aus den USA ummantelt die mit einem Ringmaß von 56 ausgestattete cenicero Limited Edition VI Robusto Gordo. Darunter befindet sich ein robustes Umblatt aus nicaraguanischem Anbau. In der Einlage des kräftigen Smokes, der in Nicaragua von Hand gerollt wurde, sind lang gereifte Tabake aus Panama und Nicaragua verarbeitet worden. Ein spannender Blend, der für dunkle Aromen von Erde, Kaffee, Torf und Zartbitterschokolade am Genießergaumen sorgt, unter die sich eine hervorragende Tabakwürze mischt. Zug und Abbrandverhalten sind in den seltensten Fällen zu bemängeln, was auf eine sorgfältige Verarbeitung der kräftigen Nicaraguanerin schließen lässt.","Hintergrund":"Mit unserer Eigenmarke cenicero geben wir unseren Kunden die Möglichkeit, in den Genuss echter Premiumtabake zu kommen, die wir aus Restbeständen namhafter Hersteller beziehen und dann von einer kleinen nicaraguanischen Meistermanufaktur in limitierten Kleinauflagen herstellen lassen. Preislich werden diese so angelegt, dass sie im Vergleich zu ähnlichen Qualitätsstufen aus dem Premiumbereich weitaus günstiger sind."},"diameter_mm":22.3,"ring":56,"length_mm":0,"length_inch":0,"format":"Robusto Gordo","manufactureOrigin":"Nicaragua","construction":"Longfiller","isBoxpressed":false,"wrapperOrigin":["USA"],"fillerOrigin":["Nicaragua","Panama"],"binderOrigin":["Nicaragua"],"binderProperty":"Broadleaf","aromaProfileManufacturer":["Erdig","Kaffee","Torf","Würzig","Zartbitter"],"strength":"Stark","smokingDuration":"45 bis 90 Min","price":4.9,"additionalNotes":"Limited"}
