{"name":"Macanudo Maduro Gigante","url":"https://www.noblego.de/macanudo-maduro-gigante/","brand":"Macanudo","series":"Maduro","details":{"Fazit":"Die Macanudo Maduro Gigante ist eine Zigarre die wahrscheinlich so gut wie jedem Genussraucher gefällt, ob dem unerfahrenen Einsteiger oder eingefleischtem Aficionado, ein guter Geschmack setzt sich in allen Kreisen durch.","Genuss":"Das ölig glänzende Connecticut Broadleaf Deckblatt aus den USA kleidet die Macanudo Maduro Gigante absolut standesgemäß. Die stimmige Mischung aus mexikanischen und dominikanischen Einlagetabaken der meisterlich gerollten Longfiller wird von einem aus Mexiko stammenden Umblatt gehalten. Der durchweg angenehm mittelkräftig erscheinende Smoke vermittelt seine klaren Aromen von Schokolade, Holz, Kaffee und Nuss über einen wunderbar cremigen Rauch, der zudem eine feine Süße sowie im weiteren Rauchverlauf zarte Nuancen schwarzen Pfeffers preisgibt. Über alle technischen Mängel erhaben, verfügt die „Große“ von Macanudo über einen tadellosen Zugwiderstand und brennt schnurgerade ab.","Hintergrund":"Mit der Maduro Gigante bedient man bei Macanudo den derzeitigen Trend hin zu Zigarren mit etwas größeren Ringmaßen. Solcher Art Zigarren genießen unter Zigarrenfreunden den Ruf von vornherein ausgewogener zu schmecken, da die eingezogene Luft durch mehrere feine Kanäle zirkulieren kann, als bei Vitolas mit kleineren Ringmaßeinheiten."},"diameter_mm":24,"ring":58,"length_mm":152,"length_inch":0,"format":"Toro","manufactureOrigin":"Dominikanische Republik","construction":"Longfiller","isBoxpressed":false,"wrapperOrigin":["USA"],"fillerOrigin":["Dominikanische Republik","Mexiko"],"binderOrigin":["Mexiko"],"wrapperType":"Connecticut Broadleaf Maduro","aromaProfileManufacturer":["Cremig","Holz","Kaffee","Pfeffer","Schokolade","Süß"],"strength":"Medium","flavourStrength":"Medium-aromatisch","smokingDuration":"90 Min oder länger","price":9.1}
