{"name":"Perdomo LOT 23 Connecticut Toro","url":"https://www.noblego.de/perdomo-lot-23-connecticut-toro-zigarren/","brand":"Perdomo","series":"LOT 23","details":{"Genussverlauf":"Die nicaraguanischen Tabake für Umblatt und Einlage stammen von einer Plantage mit der Bezeichnung LOT 23. Das hellbraune Connecticut Shade Deckblatt der Perdomo LOT 23 Connecticut Toro ist ebenfalls nicaraguanischen Ursprungs. Cremig anmutende Nuss-, Holz-, Toast-, Leder- und Pfefferaromen gibt die sehr gut verarbeitete Longfiller über einen angenehm samtigen Rauch an den Gaumen weiter. Während einer ungefähren Genusszeit von 90 Minuten zeigt sich die 15 cm lange Toro äußerst angenehm und wird zu keinem Zeitpunkt scharf oder bitter. Ein zuverlässig gutes Zug- und Abbrandverhalten sorgt für unkomplizierten sowie entspannten Genuss.","Nice to know":"Neben der Perdomo LOT 23 Connecticut Serie sind noch zwei weitere LOT 23 Serien von Perdomo erhältlich, die jeweils mit einem Maduro und einem Sun Grown Deckblatt ausgestattet sind.","Resümee":"Mit der Perdomo LOT 23 Connecticut Toro erwirbt man eine sanfte und aromatisch ausgereifte Zigarre von sehr guter Qualität. Wir wünschen viel Vergnügen beim Genuss!"},"diameter_mm":19.8,"ring":50,"length_mm":152,"length_inch":0,"format":"Toro","manufactureOrigin":"Nicaragua","construction":"Longfiller","isBoxpressed":false,"wrapperOrigin":["Nicaragua"],"WrapperTobaccoVariety":"Connecticut Shade","fillerOrigin":["Nicaragua"],"binderOrigin":["Nicaragua"],"aromaProfileManufacturer":["Cremig","Holz","Leder","Nuss","Pfeffer","Toast"],"strength":"Medium","flavourStrength":"Medium-aromatisch","smokingDuration":"45 bis 90 Min","price":11}
