{"name":"Matilde Limited Exposure No. 1 Toro","url":"https://www.noblego.de/matilde-limited-exposure-no-1-toro-zigarren/","brand":"Matilde","series":"Exposure","details":{"Genussverlauf":"Ein dunkelbraunes Maduro Deckblatt aus der Region San Andrés in Mexiko und dominikanische Einlage- und Umblatt-Tabake bilden den aromareichen Blend der Matilde Limited Exposure No. 1 Toro. Gleich mit den ersten Zügen lässt die hervorragend gearbeitete Longfiller ein feines Aroma von Schokolade erkennen, zu dem sich im weiteren Rauchverlauf angenehme Zedernholz- und Lederaromen sowie ein zarter Hauch Pfeffer gesellen. Im letzten Drittel kommen erdig-würzige Noten hinzu, die sich bis zum Ende des gut 90 Minuten andauernden Smokes am Gaumen ausmachen lassen. Die leckere Dominikanerin glänzt mit optimalem Abbrandverhalten und produziert jede Menge voluminösen Rauch bei perfekten Zugeigenschaften.","Nice to know":"Bei Matilde plant man für die kommenden Jahre jeweils eine Sonderedition im Stile der Exposure No. 1 herauszubringen. Von der schmackhaften Toro wurden dem deutschen Markt gerade einmal 100 20er Kisten zur Verfügung gestellt. Wir haben es hier also mit einer wirklich seltenen Sonderauflage zu tun.","Resümee":"Verpassen Sie es nicht, sich einige Exemplare der Matilde Limited Exposure No. 1 Toro zu sichern. Ihr reichhaltiger und ausgewogener Geschmack macht sie auf jeden Fall zu einer lohnenswerten und raren Trophäe in jedem heimischen Humidor."},"diameter_mm":19.8,"ring":50,"length_mm":152,"length_inch":0,"format":"Toro","manufactureOrigin":"Dominikanische Republik","construction":"Longfiller","isBoxpressed":false,"wrapperOrigin":["Mexico"],"fillerOrigin":["Dominikanische Republik"],"binderOrigin":["Dominikanische Republik"],"binderProperty":"San Andrés","aromaProfileManufacturer":["Erdig","Leder","Pfeffer","Schokolade","Würzig","Zedernholz"],"strength":"Medium","flavourStrength":"Medium-aromatisch","smokingDuration":"60 bis 90 Min","price":11,"additionalNotes":"Limited"}
