{"name":"Brick House Double Connecticut Mighty Mighty","url":"https://www.noblego.de/brick-house-double-connecticut-mighty-mighty/","brand":"Brick House","series":"Double Connecticut","details":{"Fazit":"Die Brick House Double Connecticut Mighty Mighty beschert Ihnen ein entspanntes und ausgiebiges Rauchvergnügen mit leckeren Aromen und viel cremigen Rauch. Ein wundervoller Smoke, den Sie zudem zu einem äußerst fairen Preis nach Hause geliefert bekommen.","Genuss":"Der Blend der Brick House Double Connecticut Mighty Mighty birgt eine spezielle Kombination aus Deck- und Umblatt, welche dergestalt eher selten auf dem gut sortierten Zigarrenmarkt anzutreffen ist. Das Aushängeschild der fantastisch gearbeiteten Double Toro ist ohne Zweifel ihr goldbraunes Connectcut Shade Deckblatt, welches wie ihr Connecticut Braoadleaf Umblatt aus den USA stammt. Für ihre Einlage wurden ausgereifte nicaraguanische Tabake gewählt. Diese aufregende Mischung sorgt neben einer ansprechenden Honigsüße, für viel Abwechslung im Aromaverlauf, der sich über komplexe Aromen von Zitronengras, Zedernholz, Leder, Erdnuss und Milchschokolade definiert. Ihr gut eingestellter Zug fördert viel cremigen Rauch zutage und macht diese Zigarre zu einem wunderbar runden Smoke.","Hintergrund":"In längst vergangenen Zeiten handelte es sich bei den Brick House Zigarren um kubanische Puros, ausgestattet mit den feinsten Tabaken, die man damals auf Kuba bekommen konnte. Drei Generationen später haben Eric und Bobby Newman den Geschmack dieser ersten Generation von Brick House Zigarren mit ausgewählten und sorgsam gereiften nicaraguanischen Tabaken in Kombination mit besonders aromareichen Deckblättern rekreiert und so vollmundige, fein ausgewogene Zigarren geschaffen, die an den Geschmack der Brick House Zigarren ihres Großvaters Julius Cäsar Newman erinnern."},"diameter_mm":23.8,"ring":60,"length_mm":152,"length_inch":0,"format":"Double Toro","manufactureOrigin":"Nicaragua","construction":"Longfiller","isBoxpressed":false,"wrapperOrigin":["USA"],"fillerOrigin":["Nicaragua"],"binderOrigin":["Connecticut"],"binderProperty":"Connecticut Shade","aromaProfileManufacturer":["Cremig","Honig","Leder","Nuss","Pfeffer","Schokolade","Süß","Zedernholz","Zitronengras"],"strength":"Medium","flavourStrength":"Medium-aromatisch","smokingDuration":"45 bis 90 Min","price":7.9}
