{"name":"Gurkha Treinta 30th Anniversary Magnum","url":"https://www.noblego.de/gurkha-treinta-30th-anniversary-magnum-zigarren/","brand":"Gurkha","series":"Treinta 30th Anniversary","details":{"Genussverlauf":"Hergestellt wird die Gurkha Treinta 30th Anniversary Magnum in Nicaragua von Hand. Die Tabake des ausladenden Gordo Formats setzen sich aus einem haselnussbraunen Ecuador Sun Grown Rosado Deckblatt und nicaraguanischen Erzeugnissen für Einlage sowie Umblatt zusammen. Der insgesamt bis zu 80 Minuten andauernde Smoke startet mit süß-säuerlichen Fruchtnoten, die von einer angenehmen Würze weißen Pfeffers begleitet werden. Im weiteren Verlauf nimmt die Intensität von Frucht und Pfeffer ab. Dafür erscheinen delikate Nuss- und Holztöne zu denen sich damit wunderbar harmonierende Toast- sowie Milchkaffeearomen gesellen. Die köstliche Premium-Longfiller verströmt über die gesamte Rauchdauer einen sehr satten, cremigen Rauch, der für ein vorzügliches Mundgefühl sorgt. Ihre sehr gute Qualität unterstreicht die Magnum durch ein nahezu perfektes Zug- und Abbrandverhalten.","Nice to know":"Der Markeninhaber Kaizad Hansotia bereiste im Jahr 1989 die berühmte Region Goa in Indien. Dort entdeckte er die zu dieser Zeit verwaiste Zigarrenmarke und kaufte kurzerhand alle Markenrechte. Wenige Zeit später gründete Hansotia die Gurkha Cigars Company mit Sitz in Miami, Florida.","Resümee":"Die Testraucher unserer Redaktion waren bereits nach den ersten Zügen an der Gurkha Treinta 30th Anniversary Magnum begeistert. Eine wahnsinnig gute Zigarre, welche dem Jubiläum von Gurkha zu aller Ehre gereicht."},"diameter_mm":23.8,"ring":60,"length_mm":152,"length_inch":0,"format":"Gordo","manufactureOrigin":"Nicaragua","construction":"Longfiller","isBoxpressed":false,"wrapperOrigin":["Ecuador"],"WrapperTobaccoVariety":"Rosado","fillerOrigin":["Nicaragua"],"binderOrigin":["Nicaragua"],"aromaProfileManufacturer":["Fruchtig","Holz","Milchkaffee","Nuss","Süß","Toast","Weißer Pfeffer"],"flavourStrength":"Medium-aromatisch","smokingDuration":"45 bis 90 Min","price":14.5}
