{"name":"Santa Damiana Classic Gigantes","url":"https://www.noblego.de/santa-damiana-classic-gigantes-zigarren/","brand":"Santa Damiana","series":"Classic","details":{"Genussverlauf":"Nebst ihrem hellbraunen Connecticut Shade Deckblatt aus den USA, besteht die Santa Damiana Classic Gigantes aus mindestens zwei Jahre lang gereiften Einlage- und Umblatt-Tabaken aus dominikanischem Anbau. Das 60er Ringmaß der milden Longfiller lässt jede Menge voluminöse Rauchentwicklung zu. Sie startet sehr mild mit zu Anfang grasig-heuigen Aromen, die im Rauchverlauf von holzigen und kakaoigen Noten verdrängt werden. Neben einer feinen Süße lässt sich dabei ebenfalls ein ganz dezenter Pfefferton ausmachen. Im letzten Drittel wird es ein wenig intensiver und ein feiner Lederton übernimmt bis zu Ende des Smokes. Die sehr gute Machart der Gigantes garantiert ein von Zug- oder Abbrandproblemen unbelastetes Rauchvergnügen.","Nice to know":"Hergestellt werden die Santa Damiana Zigarren in der Tabacalera de Garcia in La Romana, einer wunderschönen Küstenstadt im süd-östlichen Teil der Dominikanischen Republik. Die Tabacalera gilt als größter Betrieb für handgefertigte Zigarren weltweit.","Resümee":"Ob Einsteiger oder Freund des sanften Genusses, die Santa Damiana Classic Gigantes versorgt Sie bestens mit vollmundigem Geschmack, ohne jemals unangenehm zu werden."},"diameter_mm":23.8,"ring":60,"length_mm":152,"length_inch":0,"format":"Gigantes","manufactureOrigin":"Dominikanische Republik","construction":"Longfiller","isBoxpressed":false,"wrapperOrigin":["Connecticut River Valley","USA"],"WrapperTobaccoVariety":"Connecticut Shade","fillerOrigin":["Dominikanische Republik"],"binderOrigin":["Dominikanische Republik"],"aromaProfileManufacturer":["Cremig","Gras","Holz","Kakao","Leder","Pfeffer","Süß"],"strength":"Mild","flavourStrength":"Mild-aromatisch","smokingDuration":"90 Min oder länger","price":7.9}
