{"name":"RoMa Craft Tobac  CroMagnon Cranium","url":"https://www.noblego.de/roma-craft-tobac-cromagnon-cranium/","brand":"RoMa Craft Tobac","series":"CroMagnon","details":{"Fazit":"Wenn Sie von der Sorte Genussraucher sind, die von einer Zigarre eine vollmundige und ausgeprägte Aromaentfaltung erwarten, dann haben Sie mit der RoMa Craft Tobac CroMagnon Cranium genau solch einen anspruchsvollen Smoke gefunden.","Genuss":"Die RoMa Craft Tobac CroMagnon Cranium wurde von professionellen Händen im stattlichen Toro Gordo Format von Hand gerollt. Dabei wurden ihre rein nicaraguanischen Einlagetabake mit einem kamerunischen Umblatt umschlossen, und als Deckblatt ein wunderschön öliges Connecticut Braodleaf Maduro aus den USA verwendet. Dieser spannende Blend sorgt für ein komplexes Aromaspiel mit cremigen Erd-, Holz-, Kaffee-, Leder- und Schokoladenoten umschmeichelt von einer angenehm natürlich erscheinenden Süße. Der starke Smoke besitzt zudem eine vollmundige Würze, die wunderbar zu den aufkommenden Aromen passt. Technisch überzeugt die nicaraguanische Longfiller auf ganzer Linie, denn Zug und Abbrand gehen mehr als vorbildlich vonstatten.","Hintergrund":"Bei RoMa Craft Tobac stehen der Geschmack und die Qualität der Tabake und die daraus entstehenden Zigarren immer an erster Stelle. Daher ist die Präsentation der Vitolas der Marke auch eher zweitrangig, was man an den ganz einfach gehaltenen Bauchbinden der RoMa Craft Tobac Zigarren erkennen kann."},"diameter_mm":21.4,"ring":54,"length_mm":152,"length_inch":0,"format":"Toro Gordo","manufactureOrigin":"Nicaragua","construction":"Longfiller","isBoxpressed":false,"wrapperOrigin":["USA"],"fillerOrigin":["Nicaragua"],"binderOrigin":["Kamerun"],"wrapperType":"Connecticut Broadleaf Maduro","aromaProfileManufacturer":["Cremig","Erdig","Holz","Kaffee","Leder","Pfeffer","Schokolade","Süß"],"strength":"Stark","flavourStrength":"Medium-kräftig","smokingDuration":"45 bis 90 Min","price":10}
