{"name":"La Sagrada Familia Natural Robusto","url":"https://www.noblego.de/la-sagrada-familia-natural-robusto/","brand":"La Sagrada Familia","series":"La Sagrada Familia Natural","details":{"Fazit":"Die La Sagrada Familia Natural Robusto liefert anspruchsvollen Aficionados alles, was diese von einer wahren Premiumzigarre erwarten. Und das zu einem sehr annehmbaren und für diesen Hochgenuss absolut angemessenem Preis.","Genuss":"Ein schier makelloses ecuadorianisches Deckblatt der begehrten Sorte H2000 und Tabake aus den weltbekannten nicaraguanischen Anbaugebieten Jalapa (Umblatt) sowie Estelí (Einlage) bilden den Blend der meisterlich gerollten La Sagrada Familia Natural Robusto. Dieser ist von wunderbar ausgewogener Natur und bringt ein cremiges Rauchvergnügen geprägt von komplexen Schokolade-, Holz-, Heu- und Kaffeearomen samt natürlicher Süße sowie herrlich abgestimmter Würze weißen Pfeffers mit sich. Stärketechnisch bewegt sich die schmackhafte Longfiller im mittelkräftig bis kräftigen Bereich. Ihr vollmundiger Geschmack wird zudem von einem sehr dichten Rauch getragen, der sich vorzüglich an den Gaumen schmiegt.","Hintergrund":"Die Manufaktur in der die fantastischen La Sagrada Zigarren entstehen befindet sich im nicaraguanischen Tabakmekka Estelí, welches circa 150 km nördlich von der Hauptstadt Managua gelegen ist. Dabei handelt es sich um die älteste Zigarrenfabrik des Landes, die Fabrica de Tabacos Joya de Nicaragua, in der noch viele andere Premiumzigarren-Serien von bester Qualität gerollt werden."},"diameter_mm":19.8,"ring":50,"length_mm":127,"length_inch":0,"format":"Robusto","manufactureOrigin":"Nicaragua","construction":"Longfiller","isBoxpressed":false,"wrapperOrigin":["Ecuador"],"fillerOrigin":["Nicaragua"],"binderOrigin":["Nicaragua"],"wrapperType":"H2000","aromaProfileManufacturer":["Heu","Holz","Kaffee","Pfeffer","Schokolade","Süß"],"strength":"Stark","flavourStrength":"Medium-aromatisch","smokingDuration":"45 bis 90 Min","price":7}
