{"name":"C. Mendoza Petit Cetros Sumatra","url":"https://www.noblego.de/c-mendoza-petit-cetros-sumatra/","brand":"C. Mendoza","series":"","details":{"Fazit":"Mild in der Stärke und mild im Aroma bieten die C. Mendoza Petit Cetros Sumatra Rauchgenuss für Einsteiger und Liebhaber milder Zigarren. Als Smoke für zwischendurch bestens geeignet, vollendet ein frisches Pils das Aromenspiel.","Genuss":"Wie bei den meisten Tabakprodukten aus Deutschland handelt es sich auch bei den C. Mendoza Petit Cetros Sumatra um maschinell gefertigte Shortfiller Zigarren. Aber was für welche. Die Einlage wird bestückt mit edlen Tabaken aus der Karibik, Brasilien, Indonesien und der Dominikanischen Republik, das Umblatt ist indonesischer Java Tabak und das Deckblatt ein feines Sumatra. In dieser exklusiven Mischung werden Aromen von Gras und Holz transportiert, die sich cremig am Gaumen ausbreiten. Das Sumatra Deckblatt liefert noch eine dezent süße Note. Im Format steht die Petit Cetros mit 11,4 Zentimetern Länge und einem Durchmesser von 11 Millimetern zwischen einem Cigarillo und einer kleinen Zigarre. Damit verspricht sie einen Rauchgenuss von rund einer halben Stunde, der bei guten Zug- und Abbrandeigenschaften viel Freude bereitet.","Hintergrund":"Bei den C. Mendoza Zigarren ist vom Cigarillo bis zum Corona Grande Format alles dabei. Jedes Format gibt es in zwei Deckblatt-Varianten, als Sumatra oder als Mata Fina Brazil, das zu den teuersten Deckblättern der Welt zählt."},"diameter_mm":11,"ring":28,"length_mm":114,"length_inch":0,"format":"Cigarillo","manufactureOrigin":"Deutschland","construction":"Shortfiller","isBoxpressed":false,"wrapperOrigin":["Sumatra"],"fillerOrigin":["Brasilien","Karibik"],"binderOrigin":["Java"],"binderProperty":"Sandblatt","aromaProfileManufacturer":["Cremig","Gewürze","Gras","Holz"],"strength":"Mild","flavourStrength":"Mild-aromatisch","smokingDuration":"kürzer als 20 Min","price":1.2}
