{"name":"Bentley White Robusto","url":"https://www.noblego.de/bentley-white-robusto-zigarren/","brand":"Bentley","series":"Bentley White","details":{"Genussverlauf":"Das ecuadorianische Deckblatt der Bentley White Robusto schmeichelt dem Auge mit einem verlockend seidigen Glanz. Darunter haben erfahrene Roller ein nicaraguanisches Umblatt und erlesene nicaraguanische Einlagetabake platziert. Diese Mischung garantiert ein abwechslungsreiches und somit komplex wirkendes Rauchvergnügen von mild bis mittelkräftiger Natur. Nach dem Entzünden startet die durchweg sehr cremig auftretende Robusto mit gut aufeinander abgestimmten Aromen von frischem Brot, Leder, Eichenholz, Erde und mildem Pfeffer. Die Pfeffer- und Ledernoten überdauern hinüber ins zweite Rauchdrittel. Zu ihnen gesellen sich weitere Noten von Gewürzen, Toast und Kräutern. Diese lassen sich ebenfalls im finalen Rauchabschnitt am Gaumen erkennen und werden von erdigen Tönen sowie einer zarten Karamellsüße begleitet. Ein wahrlich köstlicher Zigarrengenuss, der sehr entspannt verläuft und keinerlei Zug- oder Abbrandprobleme verursacht.","Nice to know":"Wer sich für kräftigere Smokes der Marke Bentley interessiert, wird bei der Serie der Bentley Nicaragua Zigarren fündig. Klicken Sie einfach \u003ca href=\"/bentley-nicaragua-zigarren/\" title=\"Direkt zu den Bentley Nicaragua Zigarren!\" target=\"_blank\"\u003ehier\u003c/a\u003e, um zu diesen leckeren Premium-Longfillern zu gelangen.","Resümee":"Mit der Bentley White Robusto und den gesamten Zigarren dieser gelungenen Serie ergänzt die Premiummarke aus Nicaragua ihr Sortiment um einen sehr köstlichen und geschmackvollen Genuss."},"diameter_mm":19.8,"ring":50,"length_mm":127,"length_inch":0,"format":"Robusto","manufactureOrigin":"Nicaragua","isBoxpressed":false,"wrapperOrigin":["Ecuador"],"WrapperTobaccoVariety":"Connecticut Shade","fillerOrigin":["Nicaragua"],"binderOrigin":["Nicaragua"],"aromaProfileManufacturer":["Brot","Cremig","Eichenholz","Erdig","Gewürze","Karamell","Kräuter","Leder","Pfeffer","Süß","Toast"],"strength":"Medium","flavourStrength":"Mild-aromatisch","smokingDuration":"60 bis 90 Min","price":13.6}
