{"name":"Asylum Insidious Short Corona","url":"https://www.noblego.de/asylum-insidious-short-corona-zigarren/","brand":"Asylum","series":"Insidious","details":{"Genussverlauf":"Bei dem ecuadorianischen Connecticut Shade Deckblatt der Asylum Insidious Short Corona wurde ein wenig nachgeholfen, sodass man bei dem Genuss dieser leicht aromatisierten Zigarre aus Honduras einen fruchtig-süßen Geschmack auf den Lippen verspürt. Das ist bei weitem aber noch nicht alles, denn der ansonsten mit honduranischen Tabaken ausgestattete Blend verfügt ebenfalls über natürliche Aromen von Zedernholz, Kakao, Vanille und Gewürzen, auf die der fruchtig-süße Auftritt des Mundstücks bestens abgestimmt wurde. Spätestens gegen Ende des zweiten Rauchdrittels verliert die künstlich herbei geführte Süße ihren Einfluss und man genießt ab da den wahren Aromaauftritt der zehn Zentimeter langen Honduranerin, die sich bis zum Schluss sehr cremig und feinwürzig präsentiert.","Resümee":"Traditionell eingestellte Zigarrenfreunde würden zu der Asylum Insidious Short Corona wohl nur die Nase rümpfen. Da die Geschmäcker allerdings immer verschieden sind, muss man auch dieser Sorte Zigarren eine Daseinsberechtigung zusprechen können. Daher wird sie mit Sicherheit auch ihre Liebhaber finden."},"diameter_mm":17.5,"ring":44,"length_mm":101,"length_inch":0,"format":"Short Corona","manufactureOrigin":"Honduras","construction":"Longfiller","isBoxpressed":false,"wrapperOrigin":["Ecuador"],"WrapperTobaccoVariety":"Connecticut Shade","fillerOrigin":["Honduras"],"binderOrigin":["Honduras"],"aromaProfileManufacturer":["Cremig","Fruchtig","Holz","Kakao","Süß"],"strength":"Medium","flavourStrength":"Mild-aromatisch","smokingDuration":"45 bis 60 Min","price":7.1,"additionalNotes":"gesüßtes Mundstück"}
