{"name":"My Father The Judge Toro Fino","url":"https://www.noblego.de/my-father-the-judge-toro-fino/","brand":"My Father","series":"My Father The Judge","details":{"Fazit":"Mit Zigarren aus dem Hause My Father trifft man immer eine gute Wahl, dort setzt man auf allerhöchste Qualitätsstandards und kreiert aufregende Blends mit toller Aromaentfaltung. Probieren Sie die My Father The Judge Toro Fino einmal und lassen Sie sich von diesem Stück ehrlichen Zigarrenhandwerks überzeugen.","Genuss":"Das feine Sumatra Deckblatt der The Judge Toro Fino stammt aus Ecuador, ihr doppeltes Umblatt besteht aus nicaraguanischen Corojo und Criollo Tabaken. In der Einlage sind ebenfalls lang gereifte Tabake aus dem Land der tausend Vulkane verarbeitet worden. Den Blend dieser Serie hat man etwas kräftiger als man es von anderen Zigarren der My Father Manufaktur gewohnt ist, gestaltet. Die Toro Fino wird dabei allerdings nicht unangenehm, durch diese Tabakzusammenstellung wollte man eine besonders ausgewogene und vollmundige Aromaentfaltung erreichen. Ein Vorhaben, welches mehr als gelungen ist. Die My Father The Judge Toro Fino startet mit deutlichen Holz- und Mandelnoten, die von einer ansprechenden salzigen Note umspielt werden. In dem cremigen Rauch der Premium Longfiller von Don Pepin Garcia lassen sich im Rauchverlauf dann noch schmackhafte Anis-, Kaffee- und Nusstöne ausmachen, begleitet von einer leichten Säure, die dem gesamten Aromabouquet einen gewissen Extrakick verleiht.","Hintergrund":"Mit der My Father The Judge Grand Robusto, ist der Traditionsfamilie Garcia aus Nicaragua der große Wurf gelungen, denn die imposante Vitola wurde kürzlich vom Cigar Journal zur Zigarre des Jahres 2017 gekürt. Die Toro Fino besteht aus den gleichen Tabaken und steht der Grand Robusto somit in nichts nach."},"diameter_mm":20,"ring":52,"length_mm":152,"length_inch":0,"format":"","maker":"Jose Pepin Garcia","manufactureOrigin":"Nicaragua","construction":"Longfiller","isBoxpressed":true,"wrapperOrigin":["Ecuador"],"fillerOrigin":["Nicaragua"],"binderOrigin":["Nicaragua"],"binderProperty":"Sumatra","aromaProfileManufacturer":["Anis","Brioche","Cremig","Holz","Kaffee","Mandel","Nuss"],"strength":"Medium","flavourStrength":"Kräftig","smokingDuration":"45 bis 90 Min","price":18.2}
