{"name":"La Regenta 1921 Half Corona","url":"https://www.noblego.de/la-regenta-1921-half-corona-zigarren/","brand":"La Regenta","series":"1921","details":{"Genussverlauf":"Bei dem hellbraunen Deckblatt der La Regenta 1921 Half Corona handelt es sich um ein im Schatten gezogenes Criollo aus Ecuador. Ihre brasilianisch-dominikanische Einlage wird von einem Umblatt aus der Dominikanischen Republik umschlossen. Diese Mischung führt zu einem nicht sehr komplexen, dafür aber wunderbar geradlinigem Geschmack, der neben feiner Natursüße und -würze zarte Noten von Holz und Nuss hervorbringt, die hin und wieder von leichten Zimttönen untermalt werden. Gut 45 Minuten Genusszeit schenkt die schmackhafte Longfiller von den Kanaren ihrem Genießer bei optimalem Zug- sowie Abbrandverhalten.","Resümee":"Die La Regenta 1921 Half Corona ist eine leckere und cremige Vertreterin der kanarischen Zigarrenkultur. Qualitativ und geschmacklich kann sie es locker mit ähnlichen Blends der Konkurrenz aufnehmen. Probieren lohnt sich auf jeden Fall!"},"diameter_mm":17.1,"ring":43,"length_mm":101,"length_inch":0,"format":"Half Corona","manufactureOrigin":"Kanaren","construction":"Longfiller","isBoxpressed":false,"wrapperOrigin":["Ecuador"],"fillerOrigin":["Brasilien","Dominikanische Republik"],"binderOrigin":["Dominikanische Republik"],"wrapperType":"Criollo","aromaProfileManufacturer":["Cremig","Holz","Nuss","Süß","Zimt"],"strength":"Medium","smokingDuration":"45 bis 60 Min","price":8.7}
