{"name":"Macanudo Inspirado Orange Gigante","url":"https://www.noblego.de/macanudo-inspirado-orange-gigante-zigarren/","brand":"Macanudo","series":"Inspirado Orange","details":{"Genussverlauf":"Von meisterlicher Hand in Honduras gerollt, ist die Macanudo Inspirado Orange Gigante mit handverlesenen Tabaken aus Honduras, Nicaragua und der Dominikanischen Republik in der Einlage versehen. Gehalten wird diese von einem Umblatt aus Honduras, woher ebenfalls das wunderbar glatte und hellbraune Deckblatt der Longfiller stammt. Die mild bis mittelkräftige Zigarre der Traditionsmarke entfaltet angenehm cremige Aromen von Zedernholz, Kaffee und Leder, welche zusätzlich von einer passenden Süße umspielt werden. Freunde von milden Zigarren werden an der Gigante ihre wahre Freude haben, bleibt sie doch bis zum Rauchende unaufdringlich und angenehm zu genießen. Zum Einstieg in die breit gefächerte Welt des Genussrauchens ist sie somit selbstverständlich ebenfalls sehr zu empfehlen.","Nice to know":"Der äußerst bewanderte Masterblender Benji Menendez hat die Tabakmischung für die Macanudo Insprirado Orange Reihe zusammengestellt. Die Verarbeitung der leckeren Zigarren findet wie gewohnt unter höchsten Qualitätsstandards statt. Bei Macanudo setzt man besonders auf eine angemessen lange Reifezeit der ausgewählten Tabake, wodurch die Kreationen dieser Marke ihre milden und angenehm klaren Aromen erhalten.","Resümee":"Die Macanudo Inspirado Orange Gigante lässt sich zu jeder Tageszeit genießen. Wenn Ihnen der Sinn nach mildem, cremig-süßem Premiumgenuss steht, ist diese gefällige Köstlichkeit eine hervorragende Wahl."},"diameter_mm":24,"ring":60,"length_mm":152,"length_inch":0,"format":"","manufactureOrigin":"Honduras","construction":"Longfiller","isBoxpressed":false,"wrapperOrigin":["Honduras"],"fillerOrigin":["Dominikanische Republik","Honduras","Nicaragua"],"binderOrigin":["Honduras"],"wrapperType":"Olancho San Augustin","aromaProfileManufacturer":["Cremig","Kaffee","Leder","Süß","Zedernholz"],"strength":"Medium","flavourStrength":"Medium-aromatisch","smokingDuration":"60 bis 90 Min","price":7.3}
