{"name":"Santa Damiana Special Edition 2020 Toro","url":"https://www.noblego.de/santa-damiana-special-edition-2020-toro/","brand":"Santa Damiana","series":"","details":{"Genussverlauf":"Rein äußerlich betrachtet macht die Santa Damiana Special Edition 2020 Toro einen recht wertigen Eindruck. Der knapp 15 cm langen, mit einem Ringmaß von 52 versehenen Longfiller steht die zweite Bauchbinde unter der klassischen Markenbanderole sehr gut zu Gesicht. Sie verströmt einen sehr angenehmen nussig-süßen Kaltgeruch und weist eine tadellose Verarbeitung auf. Ihr dominikanisches Umblatt, die Einlagetabake aus Nicaragua und der Dominikanischen Republik werden von einem seidigen, haselnussbraunen Connecticut Shade Deckblatt aus den USA ummantelt. Im gesamten Rauchverlauf (ca. 70-80 Min.) zeigt sie sich angenehm mild. Ihr voluminöser Rauch enthält cremige Aromen von Mandeln und Zedernholz, die von blumigen und fruchtig-süßen Nuancen umspielt werden. Ein bestens eingestellter Zug und messerscharfer Abbrand machen diesen sanften und unbeschwerten Smoke zu einem rundum zufriedenstellenden Rauchvergnügen.","Nice to know":"Traditionell erscheinen die limitierten Sondereditionen von Santa Damiana in für die Marke unüblichen Formaten. Im regulären Sortiment der in Deutschland ungemein beliebten Zigarren aus der Dominikanischen Republik lässt sich daher auch keine Toro finden.","Resümee":"Der Respekt für die herrlich milde und mit delikaten Aromen aufwartenden Santa Damiana Special Edition 2020 Toro gilt ohne Zweifel den erfahrenen Masterblendern der dominikanischen Tabacalera de García. Dank deren feinen Sinn für geschmackvolle Zigarren, können Sie in den Genuss dieser eindrucksvollen Kreation kommen. Erfahrungsgemäß sind die Sondereditionen von Santa Damiana relativ zügig vergriffen. Daher sollten Sie schnell zugreifen, bevor es zu spät ist!"},"diameter_mm":20.6,"ring":52,"length_mm":152,"length_inch":0,"format":"Toro","manufactureOrigin":"Dominikanische Republik","construction":"Longfiller","isBoxpressed":false,"wrapperOrigin":["USA"],"fillerOrigin":["Dominikanische Republik","Nicaragua"],"binderOrigin":["Dominikanische Republik"],"wrapperType":"Connecticut Shade","aromaProfileManufacturer":["Cremig","Fruchtig","Mandel","Süß","Zedernholz"],"strength":"Mild","flavourStrength":"Mild-aromatisch","smokingDuration":"45 bis 90 Min","price":7.4,"additionalNotes":"Limited"}
