{"name":"Bentley Corona","url":"https://www.noblego.de/bentley-corona/","brand":"Bentley","series":"","details":{"Fazit":"Wer auf fein ausgewogene und angenehm abgestimmte Geschmacks- und Aromakompositionen mit Tiefgang schwört, der liegt mit der Bentley Corona genau richtig. Lieblingsmusik an, zurücklehnen und einfach entspannt genießen!","Genuss":"Intensiver Genuss für den Raucher von Format, diesem Anspruch hat sich der Hersteller Bentley verschrieben. Mit der Bentley Corona, welche mit den Maßen 140 mm x 18 mm wie eine wohlproportionierte Schönheit anmutet, gelingt es Bentley eindrucksvoll eben diesem Anspruch gerecht zu werden. Für den aufregenden Spagat zwischen Milde und Stärke sorgen das durchaus rar gesäte aber sehr gefragte Ecuador Rosado Deckblatt und die im wohlbekannten Jalapa Valley im Nordosten von Nicaragua sorgsam angebauten Premium-Tabake, die in Umblatt und Einlage der Bentley Corona ihre Verwendung finden. Eine ganz und gar hinreißende Komposition, die in erdig, ledrigen Tönen anklingt und von fruchtig-frischen sowie leicht nussigen Akzenten begleitet wird. Dazu gesellen sich bis zum Finale des Genusses der Bentley Corona immer wieder Anklänge angenehmen Pfeffers hinzu. Das einwandfreie Zug- und Abbrandverhalten der Bentley Corona trägt zusätzlich zu einem voll und ganz runden und klangvollen Genuss bei.","Hintergrund":"Alle von der Firma Bentley verwendeten Tabake sind handverlesen, zudem werden exquisite dreijährig fermentierte Tabake verwendet, welche den einzigartigen und aufregenden Geschmack von Bentley Nicaragua Zigarren sinn- und geschmackvoll abrunden."},"diameter_mm":18.3,"ring":46,"length_mm":140,"length_inch":0,"format":"Corona","manufactureOrigin":"Nicaragua","isBoxpressed":false,"wrapperOrigin":["Ecuador"],"fillerOrigin":["Nicaragua"],"binderOrigin":["Nicaragua"],"wrapperType":"Rosado","aromaProfileManufacturer":["Erdig","Fruchtig","Kaffee","Nuss","Pfeffer"],"strength":"Medium","smokingDuration":"20 bis 45 Min","price":12.5}
