{"name":"Macanudo Inspirado White Robusto","url":"https://www.noblego.de/macanudo-inspirado-white-robusto/","brand":"Macanudo","series":"Inspirado White","details":{"Fazit":"Eine so milde und komplexe Zigarre werden Sie selten zu einem solchen Spitzenpreis bekommen. Die Macanudo Inspirado White Robusto hat definitiv das Potenzial, eine der beliebtesten Vertreterinnen des milden Zigarrengenusses zu werden.","Genuss":"Bei dem seidig glänzenden Deckblatt der Macanudo Inspirado White Robusto handelt es sich um ein ganze sechs Jahre lang gereiftes Tabakblatt der Sorte Connecticut aus Ecuador. Die Einlagetabake der feinen Longfiller stammen aus Mexiko und Nicaragua und haben jeweils einen vierjährigen Reifeprozess hinter sich. Ein Umblatt aus Indonesien komplettiert diesen überaus schmackhaften Blend von sanfter Milde. Die Macanudo Inspirado White Robusto kann aufgrund der lang gereiften Tabake mit einer unglaublich komplexen und abwechslungsreichen Aromaentfaltung aufwarten. Ihr sahnig-cremiger Rauch ist angefüllt mit subtilen Tönen von Erde, Gras, Zedernholz, einer herrlichen süß-würzigen Note und einem sehr angenehmen Hauch von Zitrone. Der Zug der Robusto ist absolut perfekt eingestellt und der messerscharfe Abbrand trägt ebenfalls zu einem rundum gelungenen Rauchvergnügen bei.","Hintergrund":"Hergestellt werden die Macanudo Inspirado White Robustos in Honduras. Die Herstellung aller Zigarren von Macanudo unterliegt sehr hohen Qualitätsstandards. Dabei begleiten erfahrene Mitarbeiter den gesamten Herstellungsprozess von der Pflanzung der Tabake bis zur Verarbeitung zu den nahezu perfekten Vitolas."},"diameter_mm":19.8,"ring":50,"length_mm":127,"length_inch":0,"format":"Robusto","manufactureOrigin":"Honduras","construction":"Longfiller","isBoxpressed":false,"wrapperOrigin":["Ecuador"],"fillerOrigin":["Mexiko","Nicaragua"],"binderOrigin":["Indonesien"],"wrapperType":"Connecticut Shade","aromaProfileManufacturer":["Cremig","Erdig","Gras","Pfeffer","Süß","Würzig","Zedernholz","Zitrone"],"strength":"Mild","flavourStrength":"Medium-kräftig","smokingDuration":"45 bis 90 Min","price":6.4}
