{"name":"Bock y Ca Churchill Tubo","url":"https://www.noblego.de/bock-y-ca-churchill-tubo/","brand":"Bock y Ca","series":"","details":{"Fazit":"Eine milde Zigarre für alle Dom Rep Liebhaber. An einem lauen Sommerabend mit einem trockenen Rotwein bringt die Bock y Ca Churchill im Aluminium Tubo anhaltenden, sanft aromatischen Rauchgenuss.","Genuss":"Von außen wie innen einfach eine Schönheit. In der Einlage der Bock y Ca Churchill Tubo werden dominikanischer Piloto und nicaraguanischer Caribbean Seed Tabak verarbeitet. Umblatt  und Deckblatt bestehen aus ecuadorianischem Connecticut Seed. Die Churchill misst 17,5 cm in der Länge bei einem Durchmesser von 18 mm und macht schon unangezündet mächtig Eindruck. Einmal entfacht verströmt sie milde Aromen von süßem Holz und Gras mit würzigen Erd- und zum Ende hin auftretenden Pfeffernoten. Der Longfiller bietet Rauchgenuss in Spielfilmlänge und kann auch mit seinem leichten Zugwiderstand und dem geraden Abbrand voll überzeugen.","Hintergrund":"Die Marke Bock y Ca wurde schon in der zweiten Hälfte des 19. Jahrhunderts vom deutschen Emigranten Gustav Bock Müller auf Kuba gegründet und gehört damit zu den ältesten Habano-Marken. Nach dessen Tod geriet sie zunächst in Vergessenheit und wurde Ende der 1990er Jahre von dem Schweizer Tabakkonzern Villiger als dominikanische Zigarre neu aufgelegt."},"diameter_mm":18,"ring":46,"length_mm":175,"length_inch":0,"format":"Churchill","manufactureOrigin":"Dominikanische Republik","construction":"Longfiller","isBoxpressed":false,"wrapperOrigin":["Ecuador"],"fillerOrigin":["Dominikanische Republik","Nicaragua"],"binderOrigin":["Ecuador"],"wrapperType":"Connecticut Seed","aromaProfileManufacturer":["Erdig","Gras","Holz","Pfeffer"],"strength":"Mild","flavourStrength":"Medium-aromatisch","smokingDuration":"90 Min oder länger","price":9.5}
