{"name":"Rocky Patel Quarter Century Robusto","url":"https://www.noblego.de/rocky-patel-quarter-century-robusto/","brand":"Rocky Patel","series":"Quarter Century","details":{"Genussverlauf":"Alle Tabake der Rocky Patel Quarter Century Robusto haben eine enorme Reifezeit von mindestens zehn Jahren absolvieren müssen, bevor sie von den erfahrensten Rollern in der nicaraguanischen Manufaktur Tabacalera Villa Cuba zu unglaublich köstlichen Zigarren gerollt werden durften. Die mittelkräftige Premiumlongfiller setzt sich aus einem dunkelbraunen, ölig schimmernden San Andrés Deckblatt aus Mexiko, einem Umblatt und handverlesenen Einlagetabaken aus Nicaragua zusammen. Von Rauchbeginn an zeigt sich die Robusto sehr cremig. Sie offeriert ihrem Genießer nahezu perfekt ausgewogene Zedernholz- und Nussaromen, die in spannendem Wechselspiel von schokoladiger sowie fruchtiger Süße begleitet werden. Im weiteren Verlauf kommen besonders schmackhafte Würznoten dazu, die sich wunderbar in die gesamte Aromakomposition einfügen. Ein leckeres Rauchvergnügen, an dem man etwa für 60 Minuten seine helle Freude hat, ungetrübt von jeglichen Zug- oder Abbrandschwierigkeiten.","Nice to know":"Rekesh „Rocky“ Patel stammt aus Indien und machte nach seiner Einwanderung in die USA zunächst Karriere als Star-Anwalt namhafter Hollywoodstars wie Arnold Schwarzenegger oder Gene Hackman. Als er dann seine Leidenschaft für Zigarren entdeckte, verkaufte er einige Zeit später seine Kanzlei und zog für fünf Jahre ins mittelamerikanische Honduras, um alles über die Herstellung und den Vertrieb von Zigarren zu erlernen. Was danach geschah, gehört zur bis heute andauernden Erfolgsgeschichte seines Unternehmens Rocky Patel Premium Cigars.","Resümee":"Mit der Rocky Patel Quarter Century Robusto und der gesamten Serie beweist Rocky Patel einmal mehr sein feines Gespür für großartige Tabake und den daraus resultierenden Blends. Wir sind bereits begeistert und können Ihnen die delikaten Quarter Century Zigarren somit wärmstens empfehlen."},"diameter_mm":19.8,"ring":50,"length_mm":140,"length_inch":0,"format":"Robusto","manufactureOrigin":"Nicaragua","construction":"Longfiller","isBoxpressed":false,"wrapperOrigin":["Mexico"],"wrapperTobaccoVariety":["San","Andrés"],"fillerOrigin":["Nicaragua"],"binderOrigin":["Nicaragua"],"aromaProfileManufacturer":["Cremig","Fruchtig","Nuss","Schokolade","Süß"],"strength":"Medium","smokingDuration":"45 bis 60 Min","price":13}
