{"name":"Leonel Classic Churchill","url":"https://www.noblego.de/leonel-classic-churchill-zigarren/","brand":"Leonel","series":"Classic","details":{"Genussverlauf":"Der besonders ausgeglichen erscheinende Blend der Leonel Classic Churchill setzt sich aus einem hellbraunen Connecticut Shade Deckblatt (USA), einem dominikanischen Umblatt und einer nicaraguanisch-dominikanischen Einlage zusammen. Etwa 90 Minuten lang sorgt die handgerollte Longfiller für einen fein-cremigen Genuss, der dem Gaumen mit sanfter Würze sowie sehr harmonisch aufeinander abgestimmten Kaffee-, Holz-, Nuss-, Gras- und Pfefferaromen zu schmeicheln weiß. Der besonders einsteigerfreundliche Smoke verfügt darüber hinaus über einen wunderbar voluminösen Rauch und brennt gemächlich gerade ab.","Nice to know":"Die Classic Serie von Leonel wurde 2019 komplett neu aufgelegt. Im Zuge dessen wurden die milden Leckerbissen, die aktuell in insgesamt fünf Formaten erhältlich sind, mit einem frischen Kisten- und Zigarrenringdesign ausgestattet.","Resümee":"Liebhaber sanft-milder Zigarren mit ausgiebiger Rauchdauer sollten nicht lange zögern, sich die Leonel Classic Churchill zu Gemüte zu führen. Erleben Sie pure Harmonie in Zigarrenform!"},"diameter_mm":18.7,"ring":47,"length_mm":178,"length_inch":0,"format":"Churchill","manufactureOrigin":"Dominikanische Republik","construction":"Longfiller","isBoxpressed":false,"wrapperOrigin":["USA"],"wrapperTobaccoVariety":["Connecticut","Shade"],"fillerOrigin":["Dominikanische Republik","Nicaragua"],"binderOrigin":["Dominikanische Republik"],"aromaProfileManufacturer":["Cremig","Gras","Holz","Milchkaffee","Nuss","Pfeffer"],"strength":"Mild","flavourStrength":"Mild-aromatisch","smokingDuration":"45 bis 90 Min","price":7.9}
