{"name":"Casa de Garcia Connecticut Belicoso","url":"https://www.noblego.de/casa-de-garcia-connecticut-belicoso/","brand":"Casa de Garcia","series":"Connecticut","details":{"Fazit":"Die Casa de Garcia Connecticut Belicoso eignet sich nur wegen ihres günstigen Preises als Zigarre für das tägliche Rauchvergnügen. Ihre sanften Aromen bereichern den Tag zu jeder Zeit und fast jeder Gelegenheit. Ideal kombiniert mit einem Milchkaffee oder trockenen Weißwein.","Genuss":"In der Casa de Garcia Connecticut Belicoso vereinen sich Qualität, Erfahrung und ein unschlagbar günstiger Preis in einer mild-aromatischen Zigarre aus der Dominikanischen Republik. Die erfahrenen Torcedores der Tabacalera de Garcia verarbeiten ausgesuchte Tabake aus Honduras und der Dominikanischen Republik in der Einlage. Um- und Deckblatt kommen aus den USA, wobei das Umblatt ein Connecticut Broadleaf und das Deckblatt ein Connecticut Shade ist. Im Kaltgeruch verströmt der Longfiller intensive Tabaknoten mit leichten Nussnuancen. Angezündet bleibt die Casa de Garcia Connecticut Belicoso stets im milden Stärkebereich und entfaltet eine Aromenpalette, die von nussigen und holzigen Noten bis hin zu dezent scharfen und süßlichen Tönen reicht. Das Deckblatt verleiht ihr einen Hauch von Karamell. Mehr als eine Stunde darf man es sich mit dieser eleganten Dominikanerin gut gehen lassen.","Hintergrund":"Casa de Garcia Zigarren gehören zur Produktpalette des Altadis-Konzerns. Gefertigt werden sie in der Tabacalera de Garcia, die rund vier Autostunden entfernt von Santiago de las Caballeros, dem Zentrum der Zigarrenherstellung in der Dominikanischen Republik, liegt. In der Tabacalera de Garcia entstehen insgesamt 48 verschiedene Zigarrensorten in 1000 Formaten, darunter solch beliebte wie Don Diego und Santa Damiana."},"diameter_mm":21,"ring":53,"length_mm":155,"length_inch":0,"format":"Belicoso","manufactureOrigin":"Dominikanische Republik","construction":"Mediumfiller","isBoxpressed":false,"wrapperOrigin":["Connecticut River Valley"],"wrapperTobaccoVariety":["Connecticut","Shade"],"fillerOrigin":["Dominikanische Republik","Honduras"],"binderOrigin":["Broadleaf","Connecticut"],"aromaProfileManufacturer":["Holz","Karamell","Süß"],"strength":"Mild","flavourStrength":"Mild-aromatisch","smokingDuration":"45 bis 90 Min","price":3.2}
