{"name":"Brick House Double Connecticut Robusto","url":"https://www.noblego.de/brick-house-double-connecticut-robusto/","brand":"Brick House","series":"Double Connecticut","details":{"Fazit":"Eine sehr gelungene Zigarre der bekannten Marke Brick House. Die Brick House Double Connecticut Robusto wird Ihnen vorzüglich munden und viele geschmackvolle Genussmomente schenken.","Genuss":"Das Besondere an der Zusammensetzung der Brick House Double Connecticut Robusto, ist zweifelsohne die Kombination des Connecticut Shade Deckblattes, mit dem ebenfalls aus Connecticut in den USA stammenden Broadleaf Umblatt. Insgesamt gibt es wohl nur eine Handvoll anderer Vitolas auf dem Markt, die diese extravagante Zusammenstellung von Deck- und Umblatt aufweisen. Die Einlage der Double Connecticut Robusto besteht reinweg aus reifgelagerten nicaraguanischen Tabaken. Die feinen Longfiller aus Nicaragua bieten ein mild bis mittelkräftiges Rauchvergnügen mit abwechslungsreichen Aromen von Zedernholz, Zitronengras, Leder, Milchschokolade, Erdnuss und Espresso einhergehend mit einer verlockenden Honigsüße und der angenehmen Würze nicaraguanischer Tabake. Ein wunderbar eingestellter Zug sorgt für eine reichliche Rauchentwicklung, der Abbrand kann bei einigen Exemplaren zu Anfang etwas problematisch sein, korrigiert sich in den meisten Fällen jedoch im Rauchverlauf selbst.","Hintergrund":"Die Brick House Zigarren aus Nicaragua sind von sehr guter Qualität und sowohl bei Einsteigern als auch bei gestandenen Aficionados aufgrund ihrer wundervollen Aromastruktur bei mild bis mittelkräftigem Stärkegrad sehr beliebt."},"diameter_mm":21.4,"ring":54,"length_mm":101,"length_inch":0,"format":"Robusto","manufactureOrigin":"Nicaragua","construction":"Longfiller","isBoxpressed":false,"wrapperOrigin":["USA"],"wrapperTobaccoVariety":["Connecticut","Shade"],"fillerOrigin":["Nicaragua"],"binderOrigin":["Broadleaf","Connecticut"],"aromaProfileManufacturer":["Honig","Leder","Nuss","Pfeffer","Schokolade","Süß","Zedernholz","Zitronengras"],"strength":"Medium","flavourStrength":"Medium-aromatisch","smokingDuration":"45 bis 90 Min","price":6.6}
