{"name":"Alec Bradley Connecticut Torpedo","url":"https://www.noblego.de/alec-bradley-connecticut-torpedo-zigarren/","brand":"Alec Bradley","series":"Connecticut","details":{"Genussverlauf":"Das hellbraune Connecticut Shade Deckblatt der Alec Bradley Connecticut Torpedo stammt aus Ecuador. Ihr Umblatt und Teile der Einlage sind honduranischen Ursprungs. Nicaraguanische Einlagetabake machen den köstlichen Blend komplett. Hergestellt wird das einsteigerfreundliche Torpedo Format von Hand in der honduranischen Manufaktur Fabrica de Tabacos Cubanas. Ihr Genuss ist geprägt von abwechslungsreichen Zedernholz-, Kaffee-, Nuss- und Lederaromen, die von einer feinen Karamellsüße begleitet werden. Mit fortschreitendem Rauchverlauf intensiviert sich dieser köstliche Geschmack noch ein wenig. Auch ihre Würze erfährt im Zuge dessen eine sanfte Steigerung. So wird der delikaten Honduranerin mehr Profil und ein besonders schmackhaftes Genussfinale verliehen. Ein absolut vorbildliches Zug- und Abbrandverhalten unterstreicht ihre ohnehin sehr gute Verarbeitungsqualität.","Nice to know":"Zigarren mit Connecticut Shade Deckblättern zählen meist zu den milden Vertretern ihrer Zunft. Diese sind besonders gut für den Einstieg ins Genussrauchen oder für Freunde des sanfteren Zigarrengenusses geeignet.","Resümee":"Die Alec Bradley Connecticut Torpedo sorgt für viel Freude am Gaumen, ohne jemals aufdringlich zu werden. In den Humidoren von Liebhabern mild-aromatischer Smokes sollte sie daher auf keinen Fall fehlen."},"diameter_mm":20.6,"ring":52,"length_mm":155,"length_inch":0,"format":"Torpedo","manufactureOrigin":"Honduras","construction":"Longfiller","wrapperOrigin":["Ecuador"],"wrapperTobaccoVariety":["Connecticut","Shade"],"fillerOrigin":["Honduras","Nicaragua"],"binderOrigin":["Honduras"],"aromaProfileManufacturer":["Cremig","Kaffee","Karamell","Leder","Nuss","Pfeffer","Zedernholz"],"smokingDuration":"90 Min oder länger","price":7.8}
