{"name":"Personales Ligero Corojo Short Robusto","url":"https://www.noblego.de/personales-ligero-corojo-short-robusto/","brand":"Personales","series":"Ligero Corojo","details":{"Fazit":"Es scheint ein neuer Trend zu sein, dominikanische Zigarren würziger zu gestalten. Uns gefällt’s und Ihnen sicher auch. Probieren Sie die Personales Ligero Corojo Short Robusto zu einem Kaffee, dieser rundet das Aromenspektrum ideal ab.","Genuss":"Schon von Anfang an ist die Personales Ligero Corojo Short Robusto voll da. Ihr starkes Aroma wird gleich zu Beginn deutlich und der geneigte Aficionado beginnt zu erahnen, was ihn in der nächsten Dreiviertelstunde erwarten wird. Die kräftige Würze verdankt die Zigarre der Einlage aus drei dominikanischen Ligero Tabaken, die abgerundet werden durch ein Dominican Olor Umblatt und ein ecuadorianisches Corojo Deckblatt. Bei einer Länge von 10 cm ist die Short Robusto mit einem stattlichen Durchmesser von 21,4 mm ausgestattet und verspricht bei perfekten Zug- und Abbrenneigenschaften einen intensiv aromatischen Rauchgenuss. Zu Beginn leicht pfeffrig, mildert sich die Schärfe nach den ersten Zügen ab und gibt den Raum frei für Aromen von Holz und Erde. Im Rauchverlauf kommen mehr und mehr Kaffee- und Nussnoten hervor, abgerundet durch eine feine Süße und Röstaromen. Der Longfiller schließt wie er beginnt mit dezentem Pfeffer.","Hintergrund":"Die Personales Zigarren stammen aus der Manufaktur von Charles Fairmorn in der Dominikanischen Republik. In den USA 1972 gegründet befindet sich der Hauptsitz der Firma seit Ende der 1970er Jahre in Deutschland. Von hier werden die kräftigen Dominikaner in die ganze Welt vertrieben."},"diameter_mm":21.4,"ring":54,"length_mm":101,"length_inch":0,"format":"Short Robusto","manufactureOrigin":"Dominikanische Republik","construction":"Longfiller","isBoxpressed":false,"wrapperOrigin":["Ecuador"],"wrapperTobaccoVariety":["Corojo"],"fillerOrigin":["Dominikanische Republik"],"binderOrigin":["Dominikanischer Olor"],"aromaProfileManufacturer":["Kaffee","Kakao","Nuss","Röstaromen","Süß"],"strength":"Stark","flavourStrength":"Medium-aromatisch","smokingDuration":"45 bis 90 Min","price":5.5}
