{"name":"Rocky Patel Private Cellar Robusto","url":"https://www.noblego.de/rocky-patel-private-cellar-robusto/","brand":"Rocky Patel","series":"Private Cellar","details":{"Fazit":"Eine Zigarre mit dieser Ausrichtung kommt einem nur selten unter die Nase und zwischen die Lippen. Für den Sommer ist die Rocky Patel Private Cellar Robusto die richtige Wahl, nach dem Grillen mit einem fruchtigen sommerlichen Rotwein oder auch einem mild-fruchtigen Scotch.","Genuss":"Die Rocky Patel Private Cellar Robusto mit dem violetten Doppelring um ihren wohlgeformten Körper ist eine Premiumzigarre ersten Ranges aus Nicaragua. Im Kaltzug der Robusto mit den klassischen Maßen 127x20 deutet sich das süß-fruchtige der Kirsche bereits an und ein würziger Kern scheint ebenso auf. Angezündet ist sie im ersten Drittel irgendwo zwischen mittelstark und stark angesiedelt, das bewegt sich dann langsam aber stetig immer weiter in den mittelstarken Bereich. Die Würze wird durch die Kirscharomen immer schon fein kontrastiert, bei einigen Zügen ist die leicht süße Kirsche wie ein Knalleffekt da, bemerkenswert. Im zweiten Drittel geht die Würze zusammen mit der Kirsche etwas zurück in hält sich im Hintergrund. Kakao und Kaffeearomen sind jetzt präsenter und werden vom cremiger werdenden Rauch transportiert. Zum Fruchtigen gesellt sich weißer Pfeffer, das ganze wird durch Röstaromen unterstützt. Im letzten Drittel sind es die Röstaromen, der weiße Pfeffer und eine Ahnung von Kirsche, die sehr cremig geliefert werden. Der Zug ist über die gesamte Rauchdauer sehr gut, der Abbrand zeigte sich etwas unregelmäßig, das korrigiert sich aber immer von selbst. Eine Stunde dauert dieser feine und anregende Genuss.","Hintergrund":"Wie bei Rocky Patel üblich ist es schwer, Genaueres über die Zusammensetzung der Blends zu erfahren. Das Deckblatt ist ein Broadleaf aus Connecticut, das erkennt man recht eindeutig, bei Einlage und Umblatt darf man getrost auf Nicaragua tippen, denn dort wird die Zigarre hergestellt."},"diameter_mm":19.8,"ring":50,"length_mm":127,"length_inch":0,"format":"Robusto","maker":"Rocky Patel","manufactureOrigin":"Nicaragua","construction":"Longfiller","isBoxpressed":false,"wrapperOrigin":["Connecticut River Valley"],"wrapperTobaccoVariety":["Broadleaf"],"fillerOrigin":["Nicaragua"],"binderOrigin":["Nicaragua"],"aromaProfileManufacturer":["Cremig","Fruchtig","Kaffee","Kakao","Kirsche","Pfeffer","Röstaromen","Süß","Würzig","Zedernholz"],"strength":"Medium","flavourStrength":"Kräftig","smokingDuration":"45 bis 90 Min","price":7.2}
