{"name":"A.J. Fernandez Enclave Connecticut Toro","url":"https://www.noblego.de/a-j-fernandez-enclave-connecticut-toro-zigarren/","brand":"A.J. Fernandez","series":"Enclave Connecticut","details":{"Genussverlauf":"Als Einlage und Umblatt wurden für die A.J. Fernandez Enclave Connecticut Toro ausschließlich Tabake von den fruchtbaren Feldern der nicaraguanischen Plantagen des erfahrenen Premiumherstellers gewählt. Ihr Deckblatt stammt aus Ecuador, ein wunderschön fein geadertes Connecticut Shade von hellbraunem Farbton. Die Longfiller legt einen cremig-süßen Start hin und entwickelt mit fortwährendem Genuss feine Holz- sowie Lederaromen, welche von einer sanften Note weißen Pfeffers begleitet werden. Circa 80 Minuten zeigt sich die vorbildlich verarbeitete Toro angenehm mild am Gaumen. Sie lässt sich aufgrund sehr guter Zug- und Abbrandeigenschaften völlig unkompliziert bis zum letzten Zentimeter genießen.","Nice to know":"Auf den Kisten der A.J. Fernandez Enclave Connecticut Zigarren findet sich die Bezeichnung „Edición Internacional“. Damit will der Hersteller betonen, dass die Serie sich geschmacklich an die Vorlieben des internationalen Markts richtet. Für den US-Markt ist diese Serie nicht vorgesehen.","Resümee":"Wenn Sie bisher aufgrund Ihrer Vorliebe für milde Zigarren die Zigarren von A.J. Fernandez verschmäht haben, steht Ihnen nun mit der A.J. Fernandez Enclave Connecticut Toro ein delikater Blend zur Verfügung, der sanften Genuss mit feinem Premiumcharakter verspricht."},"diameter_mm":20.6,"ring":52,"length_mm":152,"length_inch":0,"format":"Toro","maker":"AJ Fernandez","manufactureOrigin":"Nicaragua","construction":"Longfiller","isBoxpressed":false,"wrapperOrigin":["Ecuador"],"wrapperTobaccoVariety":["Connecticut","Shade"],"fillerOrigin":["Nicaragua"],"binderOrigin":["Nicaragua"],"aromaProfileManufacturer":["Cremig","Holz","Leder","Süß"],"strength":"Medium","flavourStrength":"Mild-aromatisch","smokingDuration":"45 bis 90 Min","price":10.4}
