{"name":"Joya de la Romana Corona","url":"https://www.noblego.de/joya-de-la-romana-corona/","brand":"Joya de la Romana","series":"","details":{"Fazit":"In der Joya de la Romana Corona steckt jede Menge Geschmack, dazu kommt ihr unaufdringlicher Charakter, zusammen ergibt das einen fantastisch rund schmeckenden Genuss.","Genuss":"Das hellbraun glänzende Deckblatt der Joya de la Romana Corona von der Sorte Connecticut Shade sieht sehr einladend aus, darunter verbergen sich auf den Punkt gereifte Tabake, die ebenfalls alle aus dominikanischem Anbau stammen. Im cremigen Rauch der feinen Zigarre lassen sich Aromen von Schokolade, Nuss, Gras und Holz ausmachen, die herrlich mit einer sanft süßlichen Note korrelieren. Bei exzellentem Zug- und Abbrandverhalten kann sich der Genießer voll und ganz auf den leckeren Geschmack der dominikanischen Longfiller konzentrieren und so ein entspanntes Rauchvergnügen von bis zu 45 Minuten erleben.","Hintergrund":"Die Zigarren von Joya de la Romana sind bisher wohl eher Insidern bekannt, das wird sich in nächster Zeit sicher schnell ändern, denn die leckeren Smokes aus der Dominikanischen Republik betören mit einer wunderbaren Ausgewogenheit ihrer Aromen und sind preislich sehr attraktiv angesetzt."},"diameter_mm":17.1,"ring":43,"length_mm":139,"length_inch":0,"format":"Corona","manufactureOrigin":"Dominikanische Republik","construction":"Longfiller","isBoxpressed":false,"wrapperOrigin":["Dominikanische Republik"],"wrapperTobaccoVariety":["Connecticut","Shade"],"fillerOrigin":["Dominikanische Republik"],"binderOrigin":["Dominikanische Republik"],"aromaProfileManufacturer":["Cremig","Gras","Holz","Nuss","Schokolade","Süß"],"strength":"Mild","flavourStrength":"Medium-aromatisch","smokingDuration":"20 bis 45 Min","price":5.8}
