{"name":"Gurkha Treinta 30th Anniversary Robusto","url":"https://www.noblego.de/gurkha-treinta-30th-anniversary-robusto-zigarren/","brand":"Gurkha","series":"Treinta 30th Anniversary","details":{"Genussverlauf":"Hergestellt wird die Gurkha Treinta 30th Anniversary Robusto in Nicaragua von Hand. Ihre Tabake setzen sich aus einem haselnussbraunen Ecuador Sun Grown Rosado Deckblatt und nicaraguanischen Erzeugnissen für Einlage sowie Umblatt zusammen. Der insgesamt bis zu 60 Minuten andauernde Smoke startet mit süß-säuerlichen Fruchtnoten, die von einer angenehmen Würze weißen Pfeffers begleitet werden. Im weiteren Verlauf nimmt die Intensität von Frucht und Pfeffer ab. Dafür erscheinen delikate Nuss- und Holztöne zu denen sich damit wunderbar harmonierende Toast- sowie Milchkaffeearomen gesellen. Die köstliche Premium-Longfiller verströmt über die gesamte Rauchdauer einen sehr satten, cremigen Rauch, der für ein vorzügliches Mundgefühl sorgt. Ihre sehr gute Qualität unterstreicht die Robusto durch ein nahezu perfektes Zug- und Abbrandverhalten.","Nice to know":"Für die Präsentation ihrer Jubiläumsserie hat man sich bei Gurkha ebenfalls mächtig ins Zeug gelegt. Die stilvoll und in schlichtem Schwarz gestalten 21er Massivholzkisten machen einen sehr hochwertigen Eindruck und sind sogar abschließbar.","Resümee":"Sahnig-cremiger Rauch, harmonisch miteinander korrelierende Aromen und eine einwandfreie Verarbeitung verleihen der Gurkha Treinta 30th Anniversary Robusto das Prädikat „sehr gut“. Ein unglaublich gut gelungener Blend, den man gar nicht mehr aus den Händen geben möchte."},"diameter_mm":20.6,"ring":52,"length_mm":127,"length_inch":0,"format":"Robusto","manufactureOrigin":"Nicaragua","construction":"Longfiller","isBoxpressed":false,"wrapperOrigin":["Ecuador","Nicaragua"],"wrapperTobaccoVariety":["Rosado"],"fillerOrigin":["Nicaragua"],"binderOrigin":["Nicaragua"],"aromaProfileManufacturer":["Fruchtig","Holz","Milchkaffee","Nuss","Süß","Toast","Weißer Pfeffer"],"flavourStrength":"Medium-aromatisch","smokingDuration":"45 bis 90 Min","price":13.5}
