{"name":"A.J. Fernandez Enclave Connecticut Robusto","url":"https://www.noblego.de/a-j-fernandez-enclave-connecticut-robusto-zigarren/","brand":"A.J. Fernandez","series":"Enclave Connecticut","details":{"Genussverlauf":"Als Einlage und Umblatt wurden für die A.J. Fernandez Enclave Connecticut Robusto ausschließlich Tabake von den fruchtbaren Feldern der nicaraguanischen Plantagen des erfahrenen Premiumherstellers gewählt. Ihr Deckblatt stammt aus Ecuador, ein wunderschön fein geadertes Connecticut Shade von hellbraunem Farbton. Die Robusto legt einen cremig-süßen Start hin und entwickelt mit fortwährendem Genuss feine Holz- sowie Lederaromen, welche von einer sanften Note weißen Pfeffers begleitet werden. Circa 60 Minuten zeigt sich die vorbildlich verarbeitete Longfiller angenehm mild am Gaumen. Sie lässt sich aufgrund sehr guter Zug- und Abbrandeigenschaften völlig unkompliziert bis zum letzten Zentimeter genießen.","Nice to know":"Auf den Kisten der A.J. Fernandez Enclave Connecticut Zigarren findet sich die Bezeichnung „Edición Internacional“. Damit will der Hersteller betonen, dass die Serie sich geschmacklich an die Vorlieben des internationalen Markts richtet. Für den US-Markt ist diese Serie nicht vorgesehen.","Resümee":"Wenn Sie bisher aufgrund Ihrer Vorliebe für milde Zigarren die Zigarren von A.J. Fernandez verschmäht haben, steht Ihnen nun mit der A.J. Fernandez Enclave Connecticut Robusto ein delikater Blend zur Verfügung, der sanften Genuss mit feinem Premiumcharakter verspricht."},"diameter_mm":20.6,"ring":52,"length_mm":127,"length_inch":0,"format":"Robusto","maker":"AJ Fernandez","manufactureOrigin":"Nicaragua","construction":"Longfiller","isBoxpressed":false,"wrapperOrigin":["Ecuador"],"wrapperTobaccoVariety":["Connecticut","Shade"],"fillerOrigin":["Nicaragua"],"binderOrigin":["Nicaragua"],"aromaProfileManufacturer":["Cremig","Holz","Leder","Süß"],"flavourStrength":"Mild-aromatisch","smokingDuration":"45 bis 60 Min","price":9.5}
