{"name":"Oliva Serie V Melanio Torpedo","url":"https://www.noblego.de/oliva-serie-v-melanio-torpedo/","brand":"Oliva","series":"Melanio Serie V","details":{"Fazit":"Rauchen Sie Die Oliva Serie V Melanio Torpedo, und jede andere Zigarre dieser Serie auch, denn sie sind wunderbar. Dazu ein Karibischer Rum mit einer ordentlichen Portion Süße, Sie werden dahin schmelzen.","Genuss":"Die Oliva Serie V Melanio Torpedo ist eine boxpressed Zigarre aus Nicaragua. Sie misst 165 x 20 mm und ist sowohl perfekt konstruiert als auch vollkommen in ihren Eigenschaften. Absolut perfekter Zug, perfekter Abbrand. Sie ist medium bis stark, und voll-würzig. Das alles erklärt aber nicht im Ansatz warum bis jetzt jeder der diese Zigarre geraucht hat, in Lobeshymnen ausgebrochen ist. Das Schöne hier ist die fast melasse-artige Süße, die aber nicht alles überdeckt oder dominiert sondern trotz ihrer Süße ganz geschmeidig den anderen Aromen den Platz zum Entfalten lässt. Da ist Kaffee, Schwarzer Pfeffer, Leder und Zedernholz und natürlich die Würze. Lecker, vielschichtig, überragend komponiert!","Hintergrund":"Die Oliva Familie ist ursprünglich kubanischen Ursprungs und das merkt man der heutigen Produktion in Nicaragua durchaus an. Melanio Oliva gründete die Familientradition 1886 in Pinar del Rio, Kuba. Ihm zu Ehren wurde dem Nicaraguanischen Innenleben der Zigarre ein ecuadorianisches Deckblatt verpasst, das so seidig-ölig schimmert und so großartig duftet, dass der Alte, würde er heute noch leben, seine Freude daran hätte."},"diameter_mm":20,"ring":50,"length_mm":165,"length_inch":0,"format":"Torpedo","manufactureOrigin":"Nicaragua","construction":"Longfiller","isBoxpressed":true,"wrapperOrigin":["Ecuador"],"fillerOrigin":["Nicaragua"],"binderOrigin":["Nicaragua"],"aromaProfileManufacturer":["Kaffee","Schwarzer Pfeffer","Würzig","Zedernholz"],"strength":"Medium","flavourStrength":"Kräftig","smokingDuration":"45 bis 90 Min","price":22}
