{"name":"Davidoff Winston Churchill Late Hour Robusto","url":"https://www.noblego.de/davidoff-winston-churchill-late-hour-robusto/","brand":"Davidoff","series":"Winston Churchill Late Hour","details":{"Genussverlauf":"Das ecuadorianische Oscuro Deckblatt der Davidoff Winston Churchill Late Hour Robusto lockt mit feinem öligen Glanz und satter kaffeebrauner Farbe. Die nicht sichtbaren Teile ihres Blends bestehen aus einem mexikanischen San Andrés Deckblatt und einer raffinierten Mischung nicaraguanischer sowie dominikanischer Visus Tabake in ihrer Einlage. Eine sechsmonatige Sonderbehandlung wurde dem nicaraguanischen Einlagetabak zuteil. Dieser wurde in ausgedienten Scotch Single Malt Fässern gereift. Daher rührt die angenehm süß-würzige Note, die man während der gut 70 Minuten Rauchzeit genießen kann. In diesem Zeitraum entfaltet die Late Hour Robusto ein spannendes Wechselspiel, bei dem sich vollmundige Pfeffer-, Kaffee-, Schokolade-, Eichenholz-, Leder- und Gewürzaromen jeglicher Couleur ein delikates Stelldichein geben. Dabei zeigt sich die topp-verarbeitete Longfiller wunderbar cremig, mit voluminösem Rauch sowie völlig erhaben gegenüber jedweder Zug- oder Abbrandprobleme.","Nice to know":"Wie die Bezeichnung „Late Hour“ bereits vermuten lässt, sind die Zigarren dieser Serie eher für die abendlichen Stunden angedacht. Sie bringen alles mit, was gediegene After-Dinner-Zigarren benötigen und lassen sich bestens zu diversen alkoholischen Getränken genießen.","Resümee":"Die Davidoff Winston Churchill Late Hour Robusto ist eine charaktervolle Premiumzigarre mit viel Tiefgang und Geschmack. Aufgrund ihrer nicht zu verachtenden Kraft wendet sie sich an etwas geübtere Gaumen, die bereits Erfahrung mit komplexeren Zigarren sammeln konnten."},"diameter_mm":20.6,"ring":52,"length_mm":127,"length_inch":0,"format":"Robusto","manufactureOrigin":"Dominikanische Republik","construction":"Longfiller","isBoxpressed":false,"wrapperOrigin":["Ecuador"],"wrapperTobaccoVariety":["Oscuro"],"fillerOrigin":["Dominikanische Republik","Nicaragua"],"binderOrigin":["Mexiko"],"aromaProfileManufacturer":["Cremig","Eichenholz","Gewürze","Kaffee","Leder","Pfeffer","Schokolade","Süß"],"strength":"Medium","flavourStrength":"Medium-aromatisch","smokingDuration":"45 bis 90 Min","price":29}
