{"name":"Psyko Seven Natural Toro","url":"https://www.noblego.de/psyko-seven-natural-toro-zigarren/","brand":"Psyko Seven","series":"Natural","details":{"Genussverlauf":"Das haselnussbraune Sumatra Deckblatt der Psyko Seven Natural Toro wurde auf dominikanischem Boden angebaut. Ihr Umblatt ist ebenfalls ein Sumatra, das jedoch aus Mexiko stammt. In der Einlage findet sich ein Quintett aus verschiedenen Tabaksorten, die aus den USA, Mexiko, Honduras, Nicaragua und der Dominikanischen Republik kommen. Dieser aufwendig kreierte Blend führt zu einem mittelkräftigen Genuss mit komplexem Aromaverlauf. Zu Anfang wartet die 15,8 cm lange Toro mit vollmundigen Röstaromen auf, zu denen sich angenehm weiche Ledernoten gesellen. Im weiteren Verlauf entwickeln sich noch schmackhafte Noten von Nuss, Kaffee und Zedernholz, die von einer sanften Rosinensüße untermalt werden. Nach gut 70 Minuten hat die Natural Toro ihren gesamten Zauber gewirkt und hinterlässt einen begeisterten Genießer, der ebenfalls von ihren perfekten Zug- und Abbrandeigenschaften überzeugt wurde.","Resümee":"Eine sehr reizvolle Zigarre, deren spielerisch veranlagter Multi-Origin-Blend für ein aromareiches und komplexes Rauchvergnügen sorgt. Probier- und experimentierfreudige Genießer kommen mit der Psyko Seven Natural Toro voll auf ihre Kosten."},"diameter_mm":19,"ring":48,"length_mm":158,"length_inch":0,"format":"Toro","manufactureOrigin":"Dominikanische Republik","construction":"Longfiller","isBoxpressed":false,"wrapperOrigin":["Dominikanische Republik"],"wrapperTobaccoVariety":["Sumatra"],"fillerOrigin":["Dominikanische Republik","Honduras","Mexiko","Nicaragua","USA"],"binderOrigin":["Mexican Sumatra"],"aromaProfileManufacturer":["Kaffee","Leder","Minze","Nuss","Rosine","Röstaromen","Süß","Zedernholz"],"strength":"Medium","flavourStrength":"Medium-aromatisch","smokingDuration":"60 bis 90 Min","price":9.5}
