{"name":"Alec Bradley Medalist Robusto","url":"https://www.noblego.de/alec-bradley-medalist-robusto/","brand":"Alec Bradley","series":"Alec Bradley Medalist","details":{"Fazit":"Würden wir eine Medaille für gute Zigarren verleihen, bekäme die Alec Bradley Medalist Robusto definitiv eine verliehen die für feinen Geschmack und ein sehr gutes Verhältnis zwischen Preis und Leistung auszeichnet. Einsteigern bietet die sanfte Honduranerin ebenfalls die Gelegenheit, sich einmal an Zigarren mit gesteigerter Komplexität heranzuwagen.","Genuss":"Für die Alec Bradley Medalist Robusto hat man besonders feine Tabaksorten ausgewählt, die durch lange Reifung ein Maximum an Aromen bieten und das bei einer eher milden Stärkeausrichtung. So sind es schöne Aromen von Kakao, Backgewürzen, Leder, die auf sehr cremige Art und Weise an den Gaumen des geneigten Genießers gelangen. Eine feine Würznote rundet den sanften Geschmack der Medalist Robusto stimmig ab. Diese steuert der Anteil nicaraguanischer Tabake in der Einlage der leckeren Longfiller bei, der Rest des Blends stammt aus Honduras, besonders erwähnenswert dabei ist das hellbraun schimmernde Deckblatt der bekannten Sorte Connecticut Shade. Technisch zeigt sich die Vitola der milden Serie von Alec Bradley ebenfalls von einer sehr guten Qualität. Zug und Abbrand gestalten sich völlig unkompliziert und lassen einen entspannten Genuss zu, bei dem der Genießer sich ganz und gar auf den feinen Geschmack der Robusto konzentrieren kann.","Hintergrund":"In Zusammenarbeit mit Nestor Plasencia, der einen riesigen Erfahrungsschatz in der Herstellung grandioser Premiumzigarren besitzt, lässt der Präsident des Unternehmens Alec Bradley Cigars Alan Rubin die Zigarren seiner beliebten Marke entstehen. Mittlerweile ist das Portfolio von Alec Bradley zu einem richtig großen Sammelsurium verschiedener Blends geworden, in dem jeder Genussraucher mit Sicherheit einen leckeren Smoke nach seinen Vorlieben entdecken kann."},"diameter_mm":20.6,"ring":52,"length_mm":127,"length_inch":0,"format":"Robusto","manufactureOrigin":"Honduras","construction":"Longfiller","isBoxpressed":false,"wrapperOrigin":["Honduras"],"wrapperTobaccoVariety":["Connecticut","Shade"],"fillerOrigin":["Honduras","Nicaragua"],"binderOrigin":["Honduras"],"aromaProfileManufacturer":["Cremig","Gewürze","Kakao","Leder","Süß"],"strength":"Mild","flavourStrength":"Medium-aromatisch","smokingDuration":"45 bis 90 Min","price":7.4}
