{"name":"Leonel Signature Limited 2021 Maduro Toro","url":"https://www.noblego.de/leonel-signature-limited-2021-maduro-toro-zigarren/","brand":"Leonel","series":"Signature Limited 2021","details":{"Genussverlauf":"Für die Leonel Signature Limited 2021 Maduro Toro wurden ausschließlich nicaraguanische Tabake verwendet, welche lange reifen durften, um ihr volles Aromapotenzial entfalten zu können. Ihr Geschmack ist geprägt von einem erdigen Grundton und anfänglichen Pfeffernoten, an deren Stelle nach ein paar Minuten des Genusses cremige Schokolade- und Kaffeearomen treten. Dazu gesellen sich eine angenehm fruchtige Süße und feine Spitzen verschiedener Gewürznoten. Über den gesamten Genusszeitraum von etwa 70 bis 90 Minuten bleibt die bestens verarbeitete Toro im gemäßigt mittelkräftigen Bereich, bei vorbildlichen Zug- und Abbrandeigenschaften.\nDieser mittelkräftige Blend hat übrigens noch eine milde Schwesterzigarre: die \u003ca title=\"Klicken und direkt zur Leonel Signature Limited 2021 Connecticut gelangen!\" href=\"/leonel-signature-limited-2021-connecticut-toro-zigarren/\"\u003eLeonel Signature Limited 2021 Connecticut\u003c/a\u003e","Nice to know":"Bei Leonel achtet man sehr gewissenhaft auf die Einhaltung hoher Qualitätsstandards. So wird jede Zigarrenserie der Marke von speziell geschulten Teams betreut, um den Konsumenten eine gleichbleibend hohe Qualität garantieren zu können.","Resümee":"Wir freuen uns sehr, Ihnen eine so aufwendig gestaltete und interessante Zigarre wie die Leonel Signature Limited 2021 Maduro Toro anbieten zu dürfen. Auch wenn sie aufgrund ihrer Limitierung nicht lange verfügbar sein wird, stellt sie eine absolute Bereicherung für den Zigarrenmarkt dar und lässt auf weitere spannende Produkte der hervorragenden Marke hoffen."},"diameter_mm":20.6,"ring":52,"length_mm":152,"length_inch":0,"format":"Toro","manufactureOrigin":"Nicaragua","construction":"Longfiller","isBoxpressed":false,"wrapperOrigin":["Nicaragua"],"wrapperTobaccoVariety":["Maduro"],"fillerOrigin":["Nicaragua"],"binderOrigin":["Nicaragua"],"aromaProfileManufacturer":["Cremig","Erdig","Fruchtig","Kaffee","Pfeffer","Röstaromen","Schokolade","Süß"],"strength":"Medium","smokingDuration":"45 bis 90 Min","price":11.5,"additionalNotes":"Limited"}
