{"name":"My Father La Promesa Toro","url":"https://www.noblego.de/my-father-la-promesa-toro/","brand":"My Father","series":"La Promesa","details":{"Fazit":"Als Kenner der My Father Zigarren, weiß man wie großartig die Vitolas dieser Marke schmecken. Wenn Sie nicht zu diesem Kennerkreis gehören, dann gibt Ihnen der Genuss der My Father La Promesa Toro sicher einiges an Aufschluss über die helle Begeisterung für diese Zigarren.","Genuss":"Bis auf das feine Rosado Oscuro Deckblatt (Ecuador), sind alle Tabake der My Father La Promesa Toro auf den familieneigenen Plantagen der Garcias in Nicaragua gewachsen. Diese wurden vor ihrer Verwendung für mindestens zwei Jahre reifgelagert. In der Einlage der cremigen Vitola hat man größtenteils die Sorten Corojo und Criollo verarbeitet. Den Genießer erwartet ein mittelkräftiger Genuss, geprägt von komplex aufkeimenden Aromen von Nuss, Zedernholz, Milchschokolade und Karamell. Ein Hauch weißen Pfeffers rundet den Gesamtgeschmack vorzüglich ab. Knappe 15 cm reines Rauchvergnügen, mit sehr gutem Zugverhalten und messerscharfem Abbrand.","Hintergrund":"Die Tabakplantagen der Garcia Familie befinden sich größtenteils in Estelí, dem „Zigarrenmekka“ Nicaraguas. In der ertragreichen Region baut die Familie hier seit den 1960er Jahren ihre Tabake an und führt die große Tradition der einst auf Kuba ansässigen Familie fort."},"diameter_mm":20.6,"ring":52,"length_mm":152,"length_inch":0,"format":"Toro","manufactureOrigin":"Nicaragua","construction":"Longfiller","isBoxpressed":false,"wrapperOrigin":["Ecuador"],"wrapperTobaccoVariety":["Rosado"],"fillerOrigin":["Nicaragua"],"binderOrigin":["Nicaragua"],"aromaProfileManufacturer":["Cremig","Karamell","Nuss","Pfeffer","Schokolade","Zedernholz"],"strength":"Medium","flavourStrength":"Medium-aromatisch","smokingDuration":"45 bis 90 Min","price":14.2}
