{"name":"Toscano Marzio Robusto","url":"https://www.noblego.de/toscano-marzio-robusto-zigarren/","brand":"Toscano","series":"Marzio","details":{"Fazit":"Die Toscano Marzio Robusto ist sicher nicht die erste Zigarre ihrer Art, dafür jedoch mit Abstand eine der geschmackvollsten und kräftigsten unter den mit Fire Cured Tabaken versehenen Zigarren auf dem gesamten Markt.","Genuss":"Ein tiefbraunes Kentucky Dark Fire Cured aus den USA dient der Toscano Marzio Robusto als Deckblatt. Darunter liegt ein originales Sumatra Umblatt aus Indonesien. Die Einlagetabake der kräftigen Longfiller stammen aus Italien (Kentucky Dark Fire Cured) und der Dominikanischen Republik (Olor Seco). Nach der Rollung werden die fertigen Zigarren für ein Jahr in einem speziellen Aging-Room eingelagert. Das verleiht ihren vordergründig dunklen Aromen von Kaffee, Holz und Erde zusätzliche Tiefe und lässt die markante Räuchernote besonders intensiv erscheinen. Neben den genannten Aromen verfügt die Robusto ebenfalls über eine sehr angenehme Süße, die sich wunderbar mit den rauchigen Noten ergänzt. Gut 60 Minuten unterhält die italienisch-dominikanische Koproduktion ihre Genießer bei sehr guten Zug- und Abbrandverhalten.","Hintergrund":"Mit den Marzio Zigarren geht man bei Toscano neue Wege, denn bisher kannte man von der italienischen Edelmarke lediglich die konischen Toscanello Zigarillos und die schlanken teilbaren Figurados mit unterschiedlichen Aromatisierungen."},"diameter_mm":19.8,"ring":50,"length_mm":127,"length_inch":0,"format":"Robusto","manufactureOrigin":"Dominikanische Republik","isBoxpressed":false,"wrapperOrigin":["USA"],"wrapperTobaccoVariety":["Kentucky","Dark","Fired"],"fillerOrigin":["Dominikanische Republik","Italien"],"binderOrigin":["Sumatra"],"aromaProfileManufacturer":["Erdig","Holz","Kaffee","Rauchig","Süß"],"strength":"Stark","smokingDuration":"45 bis 90 Min","price":5.3}
