{"name":"Macanudo Inspirado White Toro","url":"https://www.noblego.de/macanudo-inspirado-white-toro/","brand":"Macanudo","series":"Inspirado White","details":{"Fazit":"Die Macanudo Inspirado White Toro kann man als absolute Ausnahmeerscheinung betrachten, denn in diesem Preissegment sind milde Zigarren mit einer solch komplexen Aromaentfaltung extrem selten zu finden.","Genuss":"Das mittelbraune Connecticut Shade Deckblatt der Macanudo Inspirado White Toro hat einen verlockend seidigen Glanz und stammt aus Ecuador. Sechs Jahre lang wurde es unter strengen Kontrollen gereift und hat somit wesentlichen Anteil am komplexen Geschmack der Longfiller aus Honduras. Ein indonesisches Umblatt und vier Jahre lang gereifte nicaraguanische und mexikanische Tabake bilden den hochwertigen Kern der perfekt verarbeiteten Toro. Diese raffinierte Komposition sorgt für ein fantastisch mildes Rauchvergnügen, das geprägt ist von cremigen Erd-, Gras-, Zedernholz- und Zitronenaromen. Umspielt wird dieser durchaus sommerliche Geschmack von einer süßen Würze, die hervorragend mit den zuvor genannten Aromen harmoniert. Die gewohnte Macanudo-Qualität garantiert zudem ein perfektes Zug- und Abbrandverhalten.","Hintergrund":"Milde Zigarren zu kreieren stellt einen Masterblender vor nicht allzu große Herausforderungen. Eine leichte Zigarre zu kreieren, die dazu noch geschmacklich so viel zu bieten hat wie die Macanudo Inspirado White Toro, gilt dagegen als hohe Kunst, die neben hochwertigen Rohstoffen, viel Erfahrung und Know-how erfordert."},"diameter_mm":19.8,"ring":50,"length_mm":165,"length_inch":0,"format":"Toro","manufactureOrigin":"Honduras","construction":"Longfiller","isBoxpressed":false,"wrapperOrigin":["Ecuador"],"wrapperTobaccoVariety":["Connecticut","Shade"],"fillerOrigin":["Mexiko","Nicaragua"],"binderOrigin":["Indonesien"],"aromaProfileManufacturer":["Cremig","Erdig","Gras","Pfeffer","Süß","Würzig","Zedernholz","Zitrone"],"strength":"Mild","flavourStrength":"Medium-kräftig","smokingDuration":"45 bis 90 Min","price":7.5}
