{"name":"C. Mendoza Cetros Brasil","url":"https://www.noblego.de/c-mendoza-cetros-brasil/","brand":"C. Mendoza","series":"Brasil","details":{"Fazit":"Die C. Mendoza Cetros Brasil bieten entspannten Genuss nach dem Abendessen. Mittelstark und medium-aromatisch dürfen sowohl Neulinge als auch erfahrene Aficionados zugreifen und den Abend mit einem kühlen Bier ausklingen lassen.","Genuss":"Deutschland hat sich in den vergangenen Jahren neben den Niederlanden, Italien und Belgien einen Platz an der Spitze der europäischen Zigarren und Zigarilloproduktion erobert. Mit C. Mendoza hat Schuster eine in Eigenproduktion entwickelte Marke im Angebot. Die C. Mendoza Cetros Brasil werden aus brasilianischen und karibischen Shortfiller-Tabaken in der Einlage, einem Java Umblatt und einem brasilianischen Mata Fina Deckblatt gefertigt. Die stark brasilianische Ausrichtung des Blends verspricht würzigen Rauchgenuss von einer guten halben Stunde, der den Aficionado Heu, Holz und verschiedene Gewürze mit einer ganz leichten Süße im Hintergrund herausschmecken lässt.","Hintergrund":"Die westfälische Stadt Bünde galt zu Beginn des 20. Jahrhunderts als Zentrum der Zigarrenproduktion in Deutschland. Heute werden dort nur noch in einer einzigen Fabrik Tabakwaren hergestellt. Die Manufaktur August Schuster steht seit ihrer Gründung 1909 für beste Tabakwaren aus Deutschlands einstiger Zigarrenhochburg."},"diameter_mm":13,"ring":33,"length_mm":139,"length_inch":0,"format":"Slim Panetela","manufactureOrigin":"Deutschland","construction":"Shortfiller","isBoxpressed":false,"wrapperOrigin":["Brasilien"],"wrapperTobaccoVariety":["Mata","Fina"],"fillerOrigin":["Brasilien","Karibik"],"binderOrigin":["Java"],"aromaProfileManufacturer":["Gewürze","Heu","Holz","Süß"],"strength":"Medium","flavourStrength":"Medium-aromatisch","smokingDuration":"20 bis 45 Min","price":1.5}
