{"name":"Brun del Ré Bicentenario Limited Edition Gordo ","url":"https://www.noblego.de/brun-del-re-bicentenario-limited-edition-gordo-zigarren/","brand":"Brun del Ré","series":"","details":{"Genussverlauf":"Das imposante Format mit einer Länge von 15,2 cm und einem 60er Ringmaß liegt sehr gut in der Hand und macht aufgrund der schicken Aufmachung ihrer Banderole sowie der zwei zusätzlichen Binden einen sehr hochwertigen Eindruck. Die Brun del Ré Bicentenario Limited Edition Gordo verfügt über ein feines, hellbraunes Connecticut Deckblatt aus Ecuador unter dem ein costa-ricanisches Umblatt liegt, das Einlagetabake aus Nicaragua und Costa Rica umschließt. Die ersten Züge an der sehr gut verarbeiteten Gordo sind von einer leichten Pfeffernote und zartbitteren Tönen bestimmt. Danach bildet sich ein schönes Nussaroma und die Zigarre beginnt sich mit jedem Zug cremiger zu zeigen. Ab dem zweiten Drittel nimmt man den Pfeffer nur noch als zarte Nuance im Hintergrund wahr. Das nussige Aroma intensiviert sich gleichzeitig, eine sanfte Süße kommt hinzu, die deutlich an Karamell erinnert. Zum Ende des weit über 90 Minuten andauernden Smokes tauchen noch Noten von Zedernholz auf. Der Zug der Gordo ist bestens eingestellt, hin und wieder beobachtet man einen etwas unregelmäßigen Abbrand, der sich allerdings nach wenigen Zügen von selbst korrigiert.","Nice to know":"Die Kolonialisierung Costa Ricas durch das damalige spanische Königreich begann etwa 1560 und hielt bis zum Jahr 1821 an, in dem das kleine zentralamerikanische Land seine Unabhängigkeit erklärte. Zunächst schloss man sich dem mittelamerikanischen Staatenbund an, von dem man sich dann 1838 lossagte. Die ersten freien Wahlen des Landes fanden 1889 statt.","Resümee":"Eine köstliche Sonderedition, die cremigen Rauchgenuss garantiert. Die Brun del Ré Bicentenario Limited Edition Gordo sollte man sich nicht entgehen lassen. Die leckere Costa-Ricanerin erscheint in limitierter Auflage und ist daher nur solange der Vorrat reicht, bestellbar."},"diameter_mm":23.8,"ring":60,"length_mm":152,"length_inch":0,"format":"Gordo","manufactureOrigin":"Costa Rica","construction":"Longfiller","isBoxpressed":false,"wrapperOrigin":["Ecuador"],"wrapperTobaccoVariety":["Connecticut"],"fillerOrigin":["Costa Rica","Nicaragua"],"binderOrigin":["Costa Rica"],"aromaProfileManufacturer":["Cremig","Erdig","Karamell","Nuss","Pfeffer","Süß","Zartbitter","Zedernholz"],"strength":"Medium","flavourStrength":"Medium-aromatisch","smokingDuration":"90 Min oder länger","price":13.2,"additionalNotes":"Limited"}
