{"name":"Villiger Dominican Selection Churchill","url":"https://www.noblego.de/villiger-dominican-selection-churchill/","brand":"Villiger","series":"Dominican Selection","details":{"Fazit":"Ein handgerollter Shortfiller mit einem spitzen Preis-Leistungs-Verhältnis: die Villiger Dominican Selection Churchill ist eine Zigarre, die sich für den Alltag eignet oder für Momente, in denen es etwas milder sein darf.","Genuss":"Mit der Villiger Dominican Selection Churchill erhalten Sie einen angenehmen Smoke, der mit milden Aromen und einem hervorragenden Preis-Leistungs-Verhältnis aufwartet. Die Mediumfiller-Einlage besteht aus dominikanischem Piloto und nicaraguanischem Caribbean Seed, das Umblatt stammt aus Indonesien und als Deckblatt wird ein Connecticut Seed aus Ecuador verarbeitet. Bei einer Länge von 168 mm und einem Durchmesser von 18 mm währt der Rauchgenuss der Churchill gute 90 Minuten und darüber hinaus. An Abbrand- und Zugverhalten ist absolut nichts auszusetzen. Aromatisch sind feine Noten von Frucht, Holz, Gras und auch etwas Schokolade zu erschmecken.","Hintergrund":"Zur Einführung auf dem Markt lief diese Zigarre noch unter dem Markennamen El Mundo del Tabaco. Nun hat sich die produzierende Firma Villiger entschieden, auch im Namen präsent zu sein. Es gibt zwei verschiedene Serie, die Dominican Selection und die Nicaragua Selection. Letztere ist im Vergleich zur ersten etwas rustikaler und würziger."},"diameter_mm":18,"ring":45,"length_mm":168,"length_inch":0,"format":"Churchill","manufactureOrigin":"Dominikanische Republik","construction":"Mediumfiller","isBoxpressed":false,"wrapperOrigin":["Ecuador"],"wrapperTobaccoVariety":["Connecticut","Seed"],"fillerOrigin":["Dominikanische Republik","Nicaragua"],"binderOrigin":["Indonesien"],"aromaProfileManufacturer":["Fruchtig","Gras","Holz"],"strength":"Mild","flavourStrength":"Mild-aromatisch","smokingDuration":"90 Min oder länger","price":4.8}
