{"name":"Foundation Cigars El Güegüense The Wise Man Toro Huaco","url":"https://www.noblego.de/foundation-cigars-el-gueegueense-the-wise-man-toro-huaco/","brand":"Foundation Cigars","series":"El Güegüense","details":{"Genussverlauf":"Reife nicaraguanische Corojo 99 und Criollo 98 Tabake wurden in der Foundation Cigars El Güegüense The Wise Man Toro Huaco verarbeitet. Diese verleihen der besonders vollmundig erscheinenden Longfiller einen kräftigen Gesamtauftritt, der sich geschmacklich über geradlinig eingestellte Holz-, Kakao- und Pfefferaromen äußert. Eine komplexe Zigarre ist die Toro Huaco keinesfalls, denn viel Wandlung erfährt ihr Genießer im Rauchverlauf nicht. Wenn man allerdings am Grundgeschmack der würzigen Puro Gefallen findet, hat man einen schmackhaften Smoke gefunden, der alle Vorteile einer wahren Premiumzigarre besitzt. Dass diese von erfahrenen Händen gerollt wurde, beweisen ein optimaler Zug und Abbrand.","Resümee":"An der Foundation Cigars El Güegüense The Wise Man Toro Huaco scheiden sich die Genießergeister. Dem einen ist sie nicht komplex genug und dem anderen gefällt ihr guter, gleichbleibender Geschmack. Zu welchen dieser Genießertypen Sie zählen, finden Sie wohl nur heraus, wenn Sie sich diese kräftige nicaraguanische Puro einmal zu Gemüte führen. Wir sind schon ganz gespannt auf Ihr Feedback"},"diameter_mm":22.2,"ring":56,"length_mm":152,"length_inch":0,"format":"Toro","manufactureOrigin":"Nicaragua","construction":"Longfiller","isBoxpressed":false,"wrapperOrigin":["Nicaragua"],"wrapperTobaccoVariety":["Corojo"],"fillerOrigin":["Nicaragua"],"binderOrigin":["Nicaragua"],"aromaProfileManufacturer":["Holz","Kakao","Pfeffer","Würzig"],"strength":"Medium","flavourStrength":"Medium-aromatisch","smokingDuration":"90 Min oder länger","price":15.6}
