{"name":"Alec Bradley Medalist Toro","url":"https://www.noblego.de/alec-bradley-medalist-toro/","brand":"Alec Bradley","series":"Alec Bradley Medalist","details":{"Fazit":"Eine unglaublich gute Zigarre, zu einem sehr fairen Preis. Die Alec Bradley Medalist Toro offeriert einen schmackhaften und ausgedehnten Zigarrengenuss der angenehmsten Art.","Genuss":"Das hellbraun glänzende Deckblatt der Alec Bradley Medalist Toro kommt aus Honduras und ist von der Sorte Connecticut Shade, darunter befindet sich ein Umblatt mit gleicher Herkunft. Für ihre Einlage wurde eine interessante Mischung aus nicaraguanischen und honduranischen Tabaken zusammengestellt. Die sehr gut verarbeitete Zigarre bietet ein mildes Rauchvergnügen, bei dem cremige Aromen von Kakao, Leder und diversen Backgewürzen geschmackvoll von einer sanften Würznote und dezenten Süße begleitet werden. Eine sehr leckere Kombination, die man bei dem gut eingestellten Zug und ebenmäßigen Abbrand der feinen Zigarre bis zu 90 Minuten in vollen Zügen genießen kann.","Hintergrund":"Alan Rubin, der Chef des Unternehmens Alec Bradley Cigars, bekommt seit geraumer Zeit Unterstützung, und zwar direkt aus der eigenen Familie. Damals benannte er seine Zigarrenmarke nach den Vornamen seiner beiden Söhne, die nun ihrem Vater mit voller Tatkraft zur Seite stehen. Erst vor Kurzem stellten die beiden potenziellen Nachfolger mit den Alec Bradley Blind Faith Zigarren ihre erste eigens kreierte Serie vor."},"diameter_mm":21.4,"ring":54,"length_mm":152,"length_inch":0,"format":"Toro","manufactureOrigin":"Honduras","construction":"Longfiller","isBoxpressed":false,"wrapperOrigin":["Honduras"],"wrapperTobaccoVariety":["Connecticut","Shade"],"fillerOrigin":["Honduras","Nicaragua"],"binderOrigin":["Honduras"],"aromaProfileManufacturer":["Cremig","Gewürze","Kakao","Leder","Süß"],"strength":"Mild","flavourStrength":"Medium-aromatisch","smokingDuration":"45 bis 90 Min","price":7.8}
