{"name":"Davidoff Grand Cru Robusto","url":"https://www.noblego.de/davidoff-grand-cru-robusto-zigarren/","brand":"Davidoff","series":"Grand Cru","details":{"Genussverlauf":"Die Tabake der sanft-milden Davidoff Grand Cru Robusto sind von einer herausragenden Güte und durchlaufen eine sehr anspruchsvolle Qualitätsprüfung, bevor sie den erfahrenen Rollern in der hauseigenen Manufaktur ausgehändigt werden. Im Falle der Grand Cru Robusto handelt es sich dabei um hochwertige dominikanische Umblatt- und Einlagetabake sowie wunderschöne Connecticut Seed Deckblätter aus Ecuador. Ein bis ins Detail ausgeklügelter Blend, der bei mildem Rauchverlauf eine außergewöhnliche Aromatiefe erkennen lässt. Neben einer zarten Süße sind es nussig-würzige Noten und spannende Töne diverser Edelhölzer, welche den feinen Geschmack der mit einer sagenhaften Cremigkeit aufwartenden Premium-Longfiller bestimmen. Zudem kann der Genießer sich bei absolut vorbildlichem Zug- und Abbrandverhalten vollends auf den Genuss dieser köstlichen Kreation aus dem Hause Davidoff fokussieren.","Nice to know":"Die Bezeichnung \u003cem\u003eGrand Cru\u003c/em\u003e stammt ursprünglich aus dem Weinanbau und wird in zweierlei Hinsicht verstanden. Wörtlich übersetzt bedeutet der Begriff „Großes Gewächs“ und meint entweder die sehr hohe Qualität der jeweiligen Pflanze oder Lage, in der diese gedeiht.","Resümee":"Wer noch nie im Leben eine Zigarre von Davidoff gekostet hat, dem fehlt definitiv einer der einschlägigsten Erfahrungen in seinem bisherigen Genießer-Dasein. Wenn Sie die Davidoff Grand Cru Robusto probiert haben, wissen Sie was genau hinter dieser Behauptung steckt."},"diameter_mm":21,"ring":52,"length_mm":133,"length_inch":0,"format":"Robusto","manufactureOrigin":"Dominikanische Republik","construction":"Longfiller","isBoxpressed":false,"wrapperOrigin":["Ecuador"],"wrapperTobaccoVariety":["Connecticut","Seed"],"fillerOrigin":["Dominikanische Republik"],"binderOrigin":["Dominikanische Republik"],"aromaProfileManufacturer":["Cremig","Holz","Nuss","Süß","Würzig"],"strength":"Mild","flavourStrength":"Medium-aromatisch","smokingDuration":"45 bis 90 Min","price":24.2}
