{"name":"Bentley Half Corona","url":"https://www.noblego.de/bentley-half-corona/","brand":"Bentley","series":"","details":{"Fazit":"Die Bentley Half Corona ist prädestiniert für den besonderen und intensiven Smoke zwischendurch. Genießen Sie diese außerordentlich geschmackvolle Zigarre zu einem Espresso oder auch gern zu einem Gläschen Cognac.","Genuss":"Bei Bentley Nicaragua Zigarren setzt man besonders auf die einwandfreie Qualität seiner Produkte, dies gilt zum einen für den professionellen Herstellungsprozess sowie für die Auswahl geeigneter Tabake, welche für den ausgewogenen Geschmack der Bentley Zigarren ausschlaggebend sind. Die Bentley Half Corona vereint all das in einer circa 30-minütigen äußerst sinnesanregenden Rauchdauer. Der schmackhafte Longfiller (97 mm x 18.3 mm) besteht in Einlage und Umblatt aus sorgsam gezogenen Tabaken, die aus dem berühmten Anbaugebiet Jalapa Valley im Nordosten Nicaraguas stammen. Das eindrucksvoll schimmernde Deckblatt der Half Corona ist ein Ecuador Rosado Blatt, welches aufgrund seiner Seltenheit nur für die exquisitesten Zigarren verwendet wird. Die mittelkräftige Bentley Half Corona bietet einen angenehmen Smoke, der sich im Aromenbereich zwischen schmeichelnden Noten von Holz, Erde und Leder ansiedeln lässt. Abgerundet werden diese Geschmackseindrücke von wohlig harmonisierenden Nuancen süßer Vanille und Zimt, wobei sich mit der Zeit zusätzlich ein sanfter Hauch von Eukalyptus ausmachen lässt. Ein wahres Fest für die Sinne, welches unter anderem auch durch die hervorragenden Zug- und Abbrandeigenschaften der Bentley Half Corona reibungslos und amüsant verläuft.","Hintergrund":"Wie schon auf dem ansprechend gestalteten Ring der Bentley Zigarren vermerkt, werden alle Vitolas der Bentley Nicaragua Linie von Hand gefertigt. Und zwar von ganz erfahrenen Händen nicaraguanischer Torcedores, die sich durch und durch auf ihr Handwerk verstehen."},"diameter_mm":18.3,"ring":46,"length_mm":97,"length_inch":0,"format":"Half Corona","manufactureOrigin":"Nicaragua","construction":"Longfiller","isBoxpressed":false,"wrapperOrigin":["Ecuador"],"wrapperTobaccoVariety":["Rosado"],"fillerOrigin":["Nicaragua"],"binderOrigin":["Nicaragua"],"aromaProfileManufacturer":["Erdig","Fruchtig","Holz","Leder","Vanille"],"strength":"Medium","smokingDuration":"20 bis 45 Min","price":9.8}
