{"name":"Casa de Garcia Connecticut Robusto","url":"https://www.noblego.de/casa-de-garcia-connecticut-robusto/","brand":"Casa de Garcia","series":"Connecticut","details":{"Fazit":"Eine Casa de Garcia Connecticut Robusto darf sich der geneigte Zigarrenfreund gerne auch täglich gönnen. Mit ihrer milden Stärke passt sie zum morgendlichen Kaffee ebenso wie als Starterzigarre in den Abend. Sowohl Anfänger als auch Liebhaber milder dominikanischer Zigarren wird die sanft-aromatische Robusto auf ihre Seite ziehen.","Genuss":"José Seijas und sein Team in der Tabacalera de Garcia sind stets bemüht ihren Kunden nur die besten Tabakerzeugnisse zu liefern. Aber sie wissen auch, dass nicht jeder Aficionado sich teure, qualitativ hochwertige Zigarren leisten kann. Die Casa de Garcia Connecticut Robusto erfüllt sowohl den Wunsch nach Qualität als auch einem möglichst niedrigen Preis. Feine und wohl-fermentierte Tabake aus der Dominikanischen Republik und Honduras bilden die Einlagemischung, die von einem Connecticut Broadleaf Umblatt gehalten wird und äußerlich mit einem Connecticut Shade Deckblatt abschließt, das im Kaltgeruch einen intensiven Tabakduft mit nussigen Noten versprüht. Aromatisch bewegt sich der milde Longfiller zwischen holzigen, nussigen, pfeffrigen und süßlichen Aromen. Die leichte Karamellnote, die wahrzunehmen ist, rührt vom Deckblatt her. Kleine Punktabzüge gibt es beim Abbrand, ansonsten lässt sich die Casa de Garcia Connecticut Robusto angenehme 45 Minuten lang einfach nur genießen.","Hintergrund":"Wie viele hochwertige Zigarrenmarken werden auch die Casa de Garcia Connecticut Bundles in der Tabacalera de Garcia in der Dominikanischen Republik gefertigt. 2012 wurden sie auf der IPCPR in Orlando, Florida vorgestellt und erfreuen sich seitdem, ob ihrer guten Qualität zum günstigen Preis, zunehmender Beliebtheit in Aficionado-Kreisen."},"diameter_mm":20,"ring":50,"length_mm":121,"length_inch":0,"format":"Robusto","manufactureOrigin":"Dominikanische Republik","construction":"Mediumfiller","isBoxpressed":false,"wrapperOrigin":["Connecticut River Valley"],"wrapperTobaccoVariety":["Connecticut","Shade"],"fillerOrigin":["Dominikanische Republik","Honduras"],"binderOrigin":["Broadleaf","Connecticut"],"aromaProfileManufacturer":["Holz","Karamell","Süß"],"strength":"Mild","smokingDuration":"45 bis 90 Min","price":3}
