{"name":"Cavalier Genève Inner Circle Robusto Grande","url":"https://www.noblego.de/cavalier-geneve-inner-circle-robusto-grande-zigarren/","brand":"Cavalier","series":"","details":{"Genussverlauf":"Ein schönes Jalapa Deckblatt aus Nicaragua, ein Umblatt aus Honduras sowie eine spannende Einlagemischung mit Tabaken aus den USA, Nicaragua, Honduras und der Dominikanischen Republik sind die Rohstoffe, welche die Cavalier Genève Inner Circle Robusto Grande zu einer milden Zigarre mit feinem Aromaspiel machen. Zum Start sind es nussige, holzige und ledrige Noten, die man am Gaumen verspürt. Etwas Erde und eine unterschwellige Süße gehören ebenfalls zum geschmacklichen Ensemble. Im Fortlauf steigt die Würzigkeit der Robusto Grande an und der einsteigerfreundliche Smoke wird immer cremiger. Ihr Zug- und Abbrandverhalten lässt sich ohne Zweifel als optimal bezeichnen.","Resümee":"Köstlich, cremig und sehr angenehm zu genießen. Die Cavalier Genève Inner Circle Robusto Grande ist ein Paradebeispiel für nicht allzu kräftige Zigarren, die dadurch allerdings nicht in Sachen Geschmack zurückstecken müssen."},"diameter_mm":22,"ring":54,"length_mm":127,"length_inch":0,"format":"Robusto Grande","manufactureOrigin":"Honduras","construction":"Longfiller","isBoxpressed":false,"wrapperOrigin":["Nicaragua"],"wrapperTobaccoVariety":["Jalapa"],"fillerOrigin":["Dominikanische Republik","Honduras","Nicaragua","USA"],"binderOrigin":["Honduras"],"aromaProfileManufacturer":["Cremig","Holz","Leder","Leicht Süß","Nuss","Würzig"],"strength":"Mild","flavourStrength":"Mild-aromatisch","smokingDuration":"60 bis 90 Min","price":12}
