{"name":"Joya de Nicaragua Antaño CT Corona Gorda","url":"https://www.noblego.de/joya-de-nicaragua-antano-ct-corona-gorda-zigarren/","brand":"Joya de Nicaragua","series":"Joya de Nicaragua Antaño CT","details":{"Genussverlauf":"Unter dem hellbraunen ecuadorianischen Connecticut Shade Deckblatt der Joya de Nicaragua Antaño CT Corona Gorda liegen ein Umblatt und geduldig gereifte Einlagetabake aus Nicaragua. Das schlanke Format sollte besonders gemächlich genossen werden, um ein zu heißes Rauchen und eine damit einhergehende Verfälschung des Geschmacks zu vermeiden. Wer sich daran hält, wird von der sehr gut verarbeiteten Longfiller mit einer köstlichen und intensiven Aromaentfaltung belohnt. Die ersten Züge sind von pfeffrigen Noten bestimmt, welche den Gaumen auf die kurz danach aufkommenden Nuss- und Zedernholznoten sensibilisiert. Im weiteren Verlauf spielen salzige Noten und süße Karamelltöne zusammen, zu denen sich alsbald fruchtig untermalte Kaffee- und Erdaromen gesellen. Ein köstlicher Smoke mit viel Rauchvolumen, der bei sehr geradem Abbrand und tadellosem Zug ungefähr 60 Minuten andauert.","Resümee":"Ein delikates Stück Zigarre – die Joya de Nicaragua Antaño CT Corona Gorda versprüht ihren Charme auf äußerst spielerische Art und Weise. Unbedingt probieren!"},"diameter_mm":18.3,"ring":46,"length_mm":133,"length_inch":0,"format":"Corona Gorda","manufactureOrigin":"Nicaragua","construction":"Longfiller","isBoxpressed":false,"wrapperOrigin":["Ecuador"],"wrapperTobaccoVariety":["Connecticut","Shade"],"fillerOrigin":["Nicaragua"],"binderOrigin":["Nicaragua"],"aromaProfileManufacturer":["Cremig","Erdig","Fruchtig","Holz","Kaffee","Karamell","Nuss","Pfeffer","Salzig","Süß"],"strength":"Medium","smokingDuration":"45 bis 90 Min","price":7.7}
