{"name":"Horacio Classic Maduro HM V Robusto","url":"https://www.noblego.de/horacio-classic-maduro-hm-v-robusto-zigarren/","brand":"Horacio","series":"Classic Maduro","details":{"Genussverlauf":"Die hervorragende Qualität des ecuadorianischen Maduro Deckblatts der Horacio Classic Maduro HM V Robusto lässt sich an seinem feinen öligen Glanz ablesen. Die restlichen Tabake der insgesamt mittelkräftigen Maduro-Zigarre stammen aus Costa Rica (Einlage) und Nicaragua (Umblatt/Einlage). Zu Genussbeginn wartet sie mit intensiven Holznoten auf, die von einer feinen Würze und subtilen Süße begleitet werden. Dazu mischt sich im weiteren Verlauf ein bis zum zweiten Rauchdrittel anhaltender Pfefferton. Dieser wird dann von süß untermalten Schokoladearomen abgelöst, die sich bis zum Anfang des letzten Drittels intensivieren. Dort angelangt, übernehmen grasige, ledrige und kräuterige Aromen. Das Finale läuten tiefe Erdnoten und der wiederkehrende Pfefferton ein. Eine messerscharfe Abbrandlinie und ein bestens eingestellter Zug sorgen für zuverlässigen und unkomplizierten Genuss.","Nice to know":"Die Zigarren der Marke Horacio werden von Werner Casagranda nach Deutschland importiert. Dessen Unternehmen Casagranda Cigars vertritt unter anderem ebenfalls die beliebten Marken Vegas de Santiago und Il Padrino.","Resümee":"Mit der Horacio Classic Maduro HM V Robusto genießt man eine sehr gute Zigarre, die sich durch einen etwas unkonventionellen, jedoch sehr schmackhaften Aromaverlauf von ähnlichen Produkten ihrer Mitbewerber abzuheben weiß."},"diameter_mm":21.4,"ring":54,"length_mm":127,"length_inch":0,"format":"Robusto","manufactureOrigin":"Nicaragua","construction":"Longfiller","isBoxpressed":false,"wrapperOrigin":["Ecuador"],"wrapperTobaccoVariety":["Maduro"],"fillerOrigin":["Costa Rica","Nicaragua"],"binderOrigin":["Nicaragua"],"aromaProfileManufacturer":["Gras","Holz","Leder","Pfeffer","Schokolade","Süß"],"strength":"Medium","smokingDuration":"45 bis 60 Min","price":9.9}
