{"name":"Cain Maduro 654T","url":"https://www.noblego.de/cain-maduro-654t/","brand":"Cain","series":"Maduro","details":{"Fazit":"Sind Sie der Stärke gewachsen? Die Cain Maduro 654T passt am besten zu einem ebenso vollmundigen und kräftigen Rum mit süßen Noten im Abgang.","Genuss":"Die Cain Maduro 654T hat es in sich – im wahrsten Sinne des Wortes. Denn hier vereinigen sich drei verschiedene Ligero-Sorten zu einem einzigartig starken und aromatischen Smoke. 25% Estelí Ligero, 27% Condega Ligero und 30% Jalapa Ligero bilden die Einlage, die von einem nicaraguanischen Umblatt und einem Maduro Deckblatt ebenfalls aus Nicaragua abgerundet wird. Bei so viel Power fällt es schwer, den Longfiller mit 54er Ringmaß über die Länge von 152 mm bis zum Ende zu rauchen. Es lohnt sich aber in jedem Fall, denn die Aromenpalette hat eine Menge zu bieten. Zu Beginn nussig, entfalten sich während des Smokes Noten von Zedernholz, Leder und eine kräftige Würze, die im Hintergrund auch Pfeffer und sogar etwas Süße durchscheinen lässt. Das letzte Drittel wartet mit Kakao, Erde und weiterhin viel Würze auf. Lassen Sie sich darauf ein und genießen Sie die volle Kraft des Ligero-Tabaks.","Hintergrund":"Ligero Blätter wachsen an der Spitze der Tabakpflanze und erhalten daher die meiste Sonneneinstrahlung. Sie sind dunkler und dicker als die restlichen Blätter und enthalten einen Großteil der Nähr- und Aromastoffe. Die Stärke der Blätter wird weiterhin durch die Region bestimmt, in der sie wachsen. So sind Ligeros aus Estelí die stärksten gefolgt von Ligeros aus Condega und schließlich Jalapa. Um sie genießbar zu machen, werden die Ligeros für die Cain Zigarren drei Mal fermentiert."},"diameter_mm":21.4,"ring":54,"length_mm":152,"length_inch":0,"format":"Torpedo","manufactureOrigin":"Nicaragua","construction":"Longfiller","wrapperOrigin":["Nicaragua"],"wrapperTobaccoVariety":["Maduro"],"fillerOrigin":["Nicaragua"],"binderOrigin":["Nicaragua"],"aromaProfileManufacturer":["Nuss","Pfeffer"],"strength":"Stark","flavourStrength":"Medium-kräftig","smokingDuration":"45 bis 90 Min","price":7.5}
