{"name":"Jericho Hill by Crowned Heads OBS (Robusto)","url":"https://www.noblego.de/jericho-hill-by-crowned-heads-obs/","brand":"Crowned Heads","series":"Jericho Hill","details":{"Fazit":"Nicht nur Johnny Cash Fans sollten hier zugreifen. Wer Crowned Heads kennt, wird wissen, dass hier nur die beste Qualität geboten wird. Und wer sie nicht kennt, sollte nicht zögern, mit ihnen Bekanntschaft zu machen.","Genuss":"Die Jericho Hill OBS ist ein boxpressed Robusto-Format mit 121 mm Länge und 20,6 mm Durchmesser, das gute 50 Minuten Genuss bietet. Auch beim Blend der Serie ließen sich die Macher von Johnny Cash inspirieren. Angelehnt an dessen Beinamen „Man in Black“ wird als Deckblatt mexikanischer San Andres Maduro Tabak verwendet, Umblatt und Einlage stammen aus Nicaragua, was dem Longfiller eine angenehm kräftige Würze verleiht. Aromatisch sind es besonders die Holznoten, die hervorstechen, daneben auch Nuss und Röstaromen. Der versierte Zigarrenraucher wird auch etwas Lakritz herausschmecken. Was besonders auffällt, ist die sehr gute Verarbeitung. Der Zugwiderstand ist wirklich einwandfrei und auch der Abbrand, der eine feste mittelgraue Asche hinterlässt, kann sich sehen lassen. Eine Zigarre mindestens so gut wie die Musik von Johnny Cash.","Hintergrund":"Der Name der Serie und auch einiger ihrer Formate bezieht sich auf den Song \u003cem\u003eCocaine Blues\u003c/em\u003e\u003cem\u003e. Darin bringt der\u003c/em\u003e\u003cem\u003e \u003c/em\u003eProtagonist Willy Lee seine Frau um und wird später vom Sherriff aus Jericho Hill verhaftet. Es ist die vierte Zigarrenserie von Crowned Heads. Auch hier gibt es eine Parallele zu Johnny Cash, der das vierte Kind seiner Eltern war."},"diameter_mm":20.6,"ring":52,"length_mm":121,"length_inch":0,"format":"Robusto","manufactureOrigin":"Nicaragua","construction":"Longfiller","isBoxpressed":true,"wrapperOrigin":["Mexico"],"wrapperTobaccoVariety":["San","Andres","Maduro"],"fillerOrigin":["Nicaragua"],"binderOrigin":["Nicaragua"],"aromaProfileManufacturer":["Holz","Lakritz","Nuss","Röstaromen"],"strength":"Stark","flavourStrength":"Medium-kräftig","smokingDuration":"45 bis 90 Min","price":12}
