{"name":"My Father La Gran Oferta Robusto","url":"https://www.noblego.de/my-father-la-gran-oferta-robusto-zigarren/","brand":"My Father","series":"La Gran Oferta","details":{"Genussverlauf":"Ein wunderschönes, mit öligem Glanz überzogenes Deckblatt aus Ecuador verleiht der My Father La Gran Oferta Robusto ein überaus verlockend wirkendes Antlitz. Die klassisch gestaltete Doppelbauchbinde und ein türkisfarbenes Fußband heben den eleganten Gesamteindruck der mittelkräftigen Longfiller zusätzlich hervor. Ihre Einlage- und Umblatt-Tabake sind rein nicaraguanischen Ursprungs. Sie verfügt über eine delikate Würze, die wie ihre abwechslungsreich erscheinenden Holz-, Honig-, Nuss-, Kaffee- und Schokoladearomen in einem wunderbar cremigen Rauch eingebunden sind. Begleitet werden diese von einer zunächst sehr deutlich auszumachenden Süße, die sich im letzten Drittel allerdings weniger intensiv zeigt. Im Abgang liegt zudem eine zarte Pfeffernote, die aber nichts mit der gewohnten Pfeffrigkeit anderer My Father Zigarren gemein hat. Zug und Abbrand sind schlichtweg als hervorragend zu bezeichnen.","Nice to know":"Die Zigarren der Serie La Gran Oferta von My Father gehören zu den jüngeren Projekten des weltbekannten Familienunternehmens aus Nicaragua. In Deutschland kamen die köstlichen Longfiller im Herbst 2018 auf den Markt.","Resümee":"Eine sehr schmackhafte Nicaraguanerin erhalten Sie mit der My Father La Gran Oferta Robusto. Gut 60 Minuten beschert sie Ihnen ein gehaltvolles und cremiges Rauchvergnügen auf hohem Niveau. In Begleitung zu einem nicaraguanischen Rum wie dem Flor de Cana 18 Jahre wird daraus sogar ein ganz besonders raffiniertes Genusserlebnis."},"diameter_mm":19.8,"ring":50,"length_mm":127,"length_inch":0,"format":"Robusto","manufactureOrigin":"Nicaragua","construction":"Longfiller","isBoxpressed":false,"wrapperOrigin":["Ecuador"],"wrapperTobaccoVariety":["H2000"],"fillerOrigin":["Nicaragua"],"binderOrigin":["Nicaragua"],"aromaProfileManufacturer":["Cremig","Holz","Honig","Kaffee","Leder","Nuss","Schokolade","Süß"],"strength":"Medium","flavourStrength":"Medium-aromatisch","smokingDuration":"45 bis 60 Min","price":12}
