{"name":"Davidoff Year of the Tiger Limited Edition 2022 Piramides","url":"https://www.noblego.de/davidoff-year-of-the-tiger-limited-edition-2022-piramides-zigarren/","brand":"Davidoff","series":"Limited Editions","details":{"Genussverlauf":"Die Davidoff Year of the Tiger Limited Edition 2022 Piramides ist die erste limitierte Sonderedition des dominikanischen Premiumherstellers, welche ein Connecticut Shade Deckblatt zur Schau trägt. Dabei handelt es sich um ein ecuadorianisches Erzeugnis von überragender Qualität, dem durch einen natürlichen Färbeprozess das Muster eines Tigerfells verliehen wurde. Ein sehr gelungener Effekt, der die Piramides auch optisch zu einer absoluten Klasse für sich werden lässt. Ihre Einlage besteht gänzlich aus dominikanischen Premiumtabaken, unter denen sich zwei besondere Hybrid-Tabake der unteren und mittleren Blattstufen befinden. Das Umblatt der Year of the Tiger ist ebenfalls ein Hybrid aus dominikanischem Anbau. Sahne, geröstete Nüsse und Honig werden von Davidoff als die drei Grundaromen, die sich in gleicher Reihenfolge in den verschiedenen Rauchdritteln zeigen, angegeben. Nuancierte Noten von Pfeffer, Zedernholz, Kakao, Leder und frischen Gewürzen schwingen während des gut 70 Minuten andauernden Genusses komplex im Hintergrund mit. Ein schnurgerader Abbrand und bestens eingestelltes Zugverhalten gelten für Zigarren auf diesem Topniveau als absolutes Selbstverständnis.","Nice to know":"Laut Davidoff lässt sich die Year of the Tiger Limited Edition 2022 Piramides bestens mit einem auf Rum basierenden Cocktail genießen. Die Gesamtdynamik und der aromatische Aufbau der feinen Premiumzigarre schaffen ideale Voraussetzungen für ein solches Pairing.","Resümee":"Ein an Kreativität und Raffinesse kaum zu überbietendes Meisterwerk! Die Davidoff Year of the Tiger Limited Edition 2022 Piramides ist ein sehr besonderes Zigarrenexemplar, das für jede Menge Begeisterung sorgen wird. Wir raten Ihnen rechtzeitig zu bestellen, denn erfahrungsgemäß sind die wenigen Kisten dieser über alle Maßen gefragten Sonderedition innerhalb kürzester Zeit vergriffen."},"diameter_mm":20.6,"ring":52,"length_mm":127,"length_inch":0,"format":"Piramide","manufactureOrigin":"Dominikanische Republik","construction":"Longfiller","isBoxpressed":false,"wrapperOrigin":["Ecuador"],"wrapperTobaccoVariety":["Connecticut","Shade"],"fillerOrigin":["Dominikanische Republik"],"binderOrigin":["Dominikanische Republik"],"aromaProfileManufacturer":["Cremig","Gewürze","Honig","Kakao","Leder","Nuss","Pfeffer","Sahne","Zedernholz"],"strength":"Medium","flavourStrength":"Medium-aromatisch","smokingDuration":"45 bis 90 Min","price":39,"additionalNotes":"Limited"}
