{"name":"Private Stock Longfiller No. 1","url":"https://www.noblego.de/private-stock-longfiller-no-1/","brand":"Private Stock","series":"","details":{"Fazit":"Eine sehr mild-aromatische Zigarre, an der vor allem Liebhaber mächtiger Formate ihre Freude haben werden. Nicht zu kräftig und dennoch würzig im Geschmack. Eine Zigarre mit Charme, die sich am besten zu einer Tasse Kaffee oder einem Glas milden Scotch kombinieren lässt.","Genuss":"Die Private Stock Longfiller No. 1 im Churchill-Format ist eine eher milde Zigarre, die auch ein mild-würziges und holziges Aroma aufweist. In der zweiten Rauchhälfte entwickelt sich ein dezent kräftigerer Geschmack, der mehr Würze beinhaltet, ohne dabei zu stark zu werden. Die voll-aromatischen Tabake aus der Dominikanischen Republik werden umhüllt von einem Connecticut Shade Deckblatt aus Ecuador. Zug und Abbrand sind sehr gut. Die Private Stock Longfiller No. 1 misst eine Länge von knapp 20 Zentimetern und besitzt einen Durchmesser von 19 Millimetern. Die Rauchdauer beträgt mindestens 90 Minuten."},"diameter_mm":19,"ring":48,"length_mm":196,"length_inch":0,"format":"Churchill","manufactureOrigin":"Dominikanische Republik","construction":"Longfiller","isBoxpressed":false,"wrapperOrigin":["Ecuador"],"wrapperTobaccoVariety":["Connecticut","Shade"],"fillerOrigin":["Dominikanische Republik"],"binderOrigin":["Dominikanische Republik"],"aromaProfileManufacturer":["Gewürze","Holz"],"strength":"Mild","flavourStrength":"Mild-aromatisch","smokingDuration":"90 Min oder länger","price":6.9}
