{"name":"Gilbert de Montsalvat Robusto","url":"https://www.noblego.de/gilbert-de-montsalvat-robusto/","brand":"Gilbert de Montsalvat","series":"","videoURLs":["https://www.youtube.com/watch?v=1mvZfRV_k1g"],"details":{"Fazit":"Die Gilbert de Montsalvat Robusto aus Nicaragua gehört mit Ihrem Kistendesign zu den ungewöhnlicheren Zigarren. Mittelstark und mit einer angenehmen Aromenfülle ist sie eine schöne Begleitung für einen netten Abend mit Freunden und einem eleganten Whisky.","Genuss":"Mit 12,7 Zentimetern Länge und einem Durchmesser von 19 Millimetern gehört die Gilbert de Montsalvat Robusto zu den größeren Formaten der edlen nicaraguanischen Zigarrenmarke. Mit einem Blend aus nicaraguanischen und panamaischen Tabaken in der Einlage, dem nicaraguanischen Umblatt und dem Connecticut Seed Deckblatt aus Ecuador vereint sie Tabake aus drei Provenienzen, die sich alle durch ihre besonders fruchtbaren Anbaugebiete auszeichnen. Das ergibt einen medium- aromatischen Mix aus Noten von Gras Kaffee, Holz und Nuss mit einer ganz leichten Schärfe zum Ende der rund 45 Minuten Rauchgenuss. Zug und Abbrand bleiben stets angenehm leicht und gleichmäßig.","Hintergrund":"Der Namensgeber der Gilbert de Montsalvat Zigarre ist eine fiktive Figur aus Kurzgeschichten des Markengründers und Schriftstellers Thomas Brunnschweiler, die ihm mitunter auch als Pseudonym diente. Dennoch ist er eine ganz eigene Persönlichkeit mit einer eigenen, sehr eindrucksvollen Biografie, die Reisen durch die ganze Welt und die Bekanntschaften zahlreicher wichtiger Persönlichkeiten des 20. Jahrhunderts umfasst. Die Legende besagt, dass Siegmund Freud höchstpersönlich, Gilbert de Montsalvat zur eigenen Zigarrenlinie angeregt haben soll."},"diameter_mm":19,"ring":48,"length_mm":127,"length_inch":0,"format":"Robusto","manufactureOrigin":"Nicaragua","construction":"Longfiller","isBoxpressed":false,"wrapperOrigin":["Ecuador"],"wrapperTobaccoVariety":["Connecticut","Seed"],"fillerOrigin":["Nicaragua","Panama"],"binderOrigin":["Nicaragua"],"aromaProfileManufacturer":["Gewürze","Gras","Kaffee","Nuss"],"strength":"Medium","flavourStrength":"Medium-aromatisch","smokingDuration":"45 bis 90 Min","price":6.5}
