{"name":"Bentley Churchill","url":"https://www.noblego.de/bentley-churchill/","brand":"Bentley","series":"","details":{"Fazit":"Für den Genuss der Bentley Churchill sollten Sie sich in erster Linie eines nehmen, Zeit. Denn die benötigen Sie, um den garantiert ausgedehnten Smoke dieser mittelkräftigen Vitola zu genießen. Zur Begleitung empfehlen wir einen gut dekantierten trockenen Rotwein.","Genuss":"Im Jargon eines Automobilliebhabers würde man die Bentley Churchill als das Flaggschiff der Bentley Nicaragua Zigarren bezeichnen. Dieser, höchsten Qualitätsansprüchen entsprechende Longfiller, wird von erfahrenen Zigarrenrollern aus Nicaragua handgefertigt und somit in seine tadellos anmutende Form gebracht. Die dabei verwendeten Tabake für Einlage (Caribbean Saaten aus Panama und Costa Rica) und Umblatt (Piloto) stammen aus dem berühmten Anbaugebiet Jalapa Valley im Nordosten Nicaraguas. Als etwas ganz Besonderes kann man die Wahl des Deckblattes der Bentley Churchill bezeichnen, hier verwendet man das seltene Ecuador Rosado Blatt, welches feinädrig schimmernd den Körper dieser perfekt gerollten Zigarre umschließt. Ein Zusammenspiel, welches der Bentley Churchill eine aufregende Aromenmixtur beschert. Schon der Kaltzug verrät, auf was sich der geschätzte Gaumen der Zigarrenfreunde freudig einlassen kann. Angenehm schmeichelnde Pfeffer-, Holz-, und Ledernoten paaren sich mit Anflügen von feinwürzigen Röst- und Kaffeearomen, dazu gesellt sich bisweilen eine behagliche Vanillesüße. Das größte Format aus der Bentley Nicaragua Linie besticht mit den Maßen 178 mm x 22 mm in imposanter Form und begeistert zusätzlich durch ein makelloses Zug- und Abbrandverhalten.","Hintergrund":"Bentley Nicaragua Zigarren beeindrucken durch ihre mustergültige Qualität, auf die man im Jalapa Valley nahe zur Grenze Honduras besonderes Augenmerk legt. Mit der Herstellung dieser edlen Meisterwerke werden daher nur wahre Experten der Zigarrenkunst betraut."},"diameter_mm":22,"ring":56,"length_mm":178,"length_inch":0,"format":"Churchill","manufactureOrigin":"Nicaragua","construction":"Longfiller","isBoxpressed":false,"wrapperOrigin":["Ecuador"],"wrapperTobaccoVariety":["Rosado"],"fillerOrigin":["Nicaragua"],"binderOrigin":["Nicaragua"],"aromaProfileManufacturer":["Holz","Kaffee","Leder","Pfeffer","Röstaromen","Süß","Vanille"],"strength":"Medium","flavourStrength":"Medium-aromatisch","smokingDuration":"45 bis 90 Min","price":16.7}
