{"name":"Vegas de Santiago Chaman Wide Churchill","url":"https://www.noblego.de/vegas-de-santiago-chaman-wide-churchill-zigarren/","brand":"Vegas de Santiago","series":"","details":{"Genussverlauf":"Das Deckblatt der Chaman Wide Churchill von Vegas de Santiago ist ein makellos erscheinendes Connecticut aus Ecuador. Dieses ummantelt ein nicaraguanisches Umblatt, welches die rein aus costa-ricanischen Tabaken bestehende Einlage umschließt. Durch das großzügige 56er Ringmaß verströmt die Chaman üppigen und dichten Rauch. Geschmacklich spielen sich eine sehr dominante Süße und fruchtige sowie grasige Aromen in den Vordergrund. Feine Noten von Schokolade, Leder und Holz scheinen während des gut 70 Minuten andauernden Smokes ebenfalls durch. Die sehr angenehm zu rauchende Longfiller zeigt sich in Sachen Zug und Abbrand von ihrer besten Seite.","Nice to know":"Für den Import der Vegas de Santiago Zigarren zeichnet sich Werner Casagranda verantwortlich. Der erfahrene Kenner sorgt immer wieder für neue und frische Genusseindrücke aus Costa Rica.","Resümee":"Die Vegas de Santiago Chaman Wide Churchill richtet sich an fortgeschrittene Einsteiger wie Freunde milderer Zigarren gleichermaßen. Wer den besonderen Geschmack der Tabake aus Costa Rica erleben möchte, trifft mit dieser gelungenen Kreation eine sehr gute Wahl."},"diameter_mm":22.2,"ring":56,"length_mm":139,"length_inch":0,"format":"Wide Churchill","manufactureOrigin":"Costa Rica","construction":"Longfiller","isBoxpressed":false,"wrapperOrigin":["Ecuador"],"wrapperTobaccoVariety":["Connecticut"],"fillerOrigin":["Costa Rica"],"binderOrigin":["Nicaragua"],"aromaProfileManufacturer":["Fruchtig","Gras","Holz","Leder","Schokolade","Süß"],"flavourStrength":"Mild-aromatisch","smokingDuration":"60 bis 90 Min","price":9.5}
