{"name":"La Aroma del Caribe Base Line Robusto Grande","url":"https://www.noblego.de/la-aroma-del-caribe-base-line-robusto-grande-zigarren/","brand":"La Aroma del Caribe","series":"La Aroma del Caribe Base Line","details":{"Genussverlauf":"Eine Zigarre wie die La Aroma del Caribe Base Line Robusto Grande vermittelt den Geschmack nicaraguanischer Tabake auf besonders authentische Weise. Sie verfügt über ein sattbraunes Connecticut Broadleaf Deckblatt, eine Sorte, die für ihre reichhaltigen und intensiven Aromen geschätzt wird. So ist die schmackhafte Nicaraguanerin auch gleich von Beginn an voll da und verströmt würzig unterlegte Kakao-, Holz- und Toastaromen. Im weiteren Verlauf treten dann noch erdige und ledrige Noten auf den Plan, welche dem gesamten Auftritt der handgerollten Longfiller zusätzliche Tiefe verleihen. Hin und wieder keimen feine Pfeffer- und Karamelltöne auf. Das Finale wird bestimmt von unaufdringlichen, herben Zartbitterschokoladearomen, bis der kraftvolle Smoke nach gut 60 Minuten dem Ende zu geht.","Nice to know":"Die bei gestandenen Aficionados sehr gefragte Marke La Aroma del Caribe wurde vom Unternehmen Ashton Cigars ins Leben gerufen. Hergestellt werden die geschmackvollen Puros in der nicaraguanischen Manufaktur von Don Pepin Garcia.","Résumé":"Von der La Aroma del Caribe Base Line Robusto Grande sollten sich Genießer angesprochen fühlen, die einen charaktervollen und kräftigen Zigarrengenuss bevorzugen."},"diameter_mm":21.4,"ring":54,"length_mm":133,"length_inch":0,"format":"Robusto Grande","manufactureOrigin":"Nicaragua","construction":"Longfiller","isBoxpressed":false,"wrapperOrigin":["Nicaragua"],"wrapperTobaccoVariety":["Connecticut","Broadleaf"],"fillerOrigin":["Nicaragua"],"binderOrigin":["Nicaragua"],"aromaProfileManufacturer":["Erdig","Holz","Kakao","Leder","Toast","Zartbitter"],"strength":"Stark","flavourStrength":"Medium-aromatisch","smokingDuration":"45 bis 90 Min","price":7.9}
