{"name":"Perdomo LOT 23 Natural Sun Grown Gordito","url":"https://www.noblego.de/perdomo-lot-23-natural-sun-grown-gordito-zigarren/","brand":"Perdomo","series":"LOT 23","details":{"Genussverlauf":"Das Deckblatt der Perdomo LOT 23 Natural Sun Grown Gordito ist ein Connecticut Seed. Wie die Tabake ihrer Einlage und des Umblatts stammt dieses aus Nicaragua. Die 11,4 cm lange Puro ist vom Start weg präsent mit cremig unterlegten Nuss-, Holz- und Erdaromen, die von der delikaten Würze der nicaraguanischen Tabake vorzüglich getragen werden. Feine Spitzen von Kaffee und Leder lasen sich in dem gut 45 bis 60-minütigen Rauchverlauf ebenfalls ausmachen. Fruchtig-süße Noten im Hintergrund runden den angenehmen Genuss trefflich ab. Insgesamt zeigt sich die Natural Sun Grown Gordito aus dem Hause Perdomo sehr ausgewogen und balanciert. Ihr Zug- und Abbrandverhalten lässt sich als nahezu perfekt bezeichnen.","Nice to know":"Die Vorfahren von Nick Perdomo Jr. Stammen aus Kuba. Von dort mussten große Teile der Familie im Zuge der kubanischen Revolution fliehen. Ihre neue Heimat fanden die Perdomos wie viele ihrer Landsleute in Nicaragua, wo die meisten von ihnen das auf Kuba erlernte Tabakhandwerk fortführten.","Resümee":"Eine sehr geschmackvolle Zigarre mit großem Ringmaß und delikater Aromaentfaltung. Die Perdomo LOT 23 Natural Sun Grown Gordito zaubert jedem Liebhaber nicaraguanischer Zigarren im Nu ein zufriedenes Lächeln ins Gesicht."},"diameter_mm":23.8,"ring":60,"length_mm":114,"length_inch":0,"format":"Gordito","manufactureOrigin":"Nicaragua","construction":"Longfiller","isBoxpressed":false,"wrapperOrigin":["Nicaragua"],"wrapperTobaccoVariety":["Connecticut","Seed"],"fillerOrigin":["Nicaragua"],"binderOrigin":["Nicaragua"],"aromaProfileManufacturer":["Cremig","Fruchtig","Holz","Kaffee","Leder","Nuss","Süß"],"strength":"Medium","flavourStrength":"Medium-aromatisch","smokingDuration":"45 bis 60 Min","price":9.2}
