{"name":"Private Stock Mediumfiller Tubos No. 1","url":"https://www.noblego.de/private-stock-mediumfiller-tubos-no-1/","brand":"Private Stock","series":"","details":{"Fazit":"Private Stock Mediumfiller No. 1 sind große, elegante Zigarren mit sehr mildem Rauch und karibischen Aromen. Als Mediumfiller sind sie äußerst preisgünstig, gemessen an der Qualität der Inhaltsstoffe. Ein süffiger Rumcocktail passt ganz hervorragend dazu.","Genuss":"Das Deckblatt ist ein hochwertiges Connecticut Shade aus Ecuador. Darunter liegt ein Connecticut Umblatt. Dieses wiederum umhüllt die Mediumfiller-Einlage aus der Dominikanischen Republik. Diese Tabaksorten sorgen für einen milden Rauch mit den karibischen Geschmacksnoten von Pfeffer, Schokolade und Zedernholz. Außerdem schmeckt man die Urwalderde der ecuadorianischen Regenwälder. Die Private Stock Mediumfiller No. 1 besitzt ein stattliches Format von 20 Millimeter im Durchmesser und 175 Millimeter in der Länge. Es handelt sich also um ein Churchill-Format, das beim genussvollen und bedächtigen Rauchen über eine Stunde lang Genuss liefern kann.","Hintergrund":"Die Bezeichnung Mediumfiller kennzeichnet die Private Stock Zigarren als qualitativ durchaus sehr gute Produkte, deren Tabak-Einlage aus mittelgroßen Tabakstücken besteht, die bei der Herstellung der Longfiller übrig geblieben sind. Zusätzlich wird die Einlage der Private Stock Mediumfiller No. 1 Zigarren mit einem San Vicente Tabakblatt aus der Dominikanischen Republik aufgerüstet. Dies steigert nicht nur die Qualität des Aufbaus, sondern auch die geschmacklichen Eigenschaften.\u003cbr\u003e\u003c/br\u003e \u003cstrong\u003e\u003c/strong\u003e"},"diameter_mm":20,"ring":50,"length_mm":175,"length_inch":0,"format":"Churchill","manufactureOrigin":"Dominikanische Republik","construction":"Mediumfiller","isBoxpressed":false,"wrapperOrigin":["Ecuador"],"wrapperTobaccoVariety":["Connecticut","Shade"],"fillerOrigin":["Dominikanische Republik"],"binderOrigin":["Connecticut"],"aromaProfileManufacturer":["Erdig","Gewürze","Nuss","Pfeffer","Zedernholz"],"strength":"Mild","flavourStrength":"Mild-aromatisch","smokingDuration":"45 bis 90 Min","price":5.6}
