{"name":"Macanudo Vintage 2000 No. VIII","url":"https://www.noblego.de/macanudo-vintage-2000-no-viii/","brand":"Macanudo","series":"Vintage 2000","details":{"Fazit":"Best of the best – so könnte sich die Macanudo Vintage 2000 No. VIII bezeichnen. Eine edle Tabakmischung in exquisiter Verarbeitung bringt ein harmonisches Aromenspektrum. Ob zum nachmittäglichen Kaffee oder zum abendlichen Digestif, die Robusto ist jederzeit der richtige Begleiter.","Genuss":"Wer edlen dominikanischen Genuss will, sollte die Macanudo Vintage 2000 No. VIII probieren. Sie ist ein echtes Meisterwerk in Verarbeitung und Geschmack. Hier wurde ganz besonders Wert auf die Erlesenheit der Tabake gelegt, nur das Beste ist gerade gut genug und so wird auch nur alle paar Jahre eine Vintage Zigarre auf den Markt gebracht. Im Jahr 2000 waren die Bedingungen für ein ideales Wachstum außerordentlich. Das mexikanische San Andrés Umblatt  wurde zu 50 % Prozent länger an der Pflanze gelassen als üblich und danach in Palmblättern zur weiteren Reifung gelagert. Auch das Connecticut Shade Deckblatt wurde einige Jahre in geeigneten Räumen gelagert, um sein intensives Aroma auszuprägen. In der Einlage finden sich dominikanische und  mexikanische Tabake desselben Jahrgangs. Dieser Blend verleiht der mittelstarken Robusto ein ausgewogenes und blumiges Aroma mit Zedernholz-, Kaffee- und Schokoladennoten. Rund eine Stunde Rauchgenuss beschert der 14 Zentimeter lange und 20 Millimeter dicke Longfiller.","Hintergrund":"Das Jahr 2000 war seit 1970 erst das sechste Jahr, in dem die Tabake den Masterblendern von Macanudo gut genug waren, um als Deckblatt für die Vintage Serie Verwendung zu finden. Die Macanudo Vintage 2000 Serie erscheint in vier Formaten: No. I Churchill, No. II Corona, No. VIII Robusto und No. X Toro."},"diameter_mm":20,"ring":50,"length_mm":140,"length_inch":0,"format":"Robusto","manufactureOrigin":"Dominikanische Republik","construction":"Longfiller","isBoxpressed":false,"wrapperOrigin":["Connecticut River Valley"],"wrapperTobaccoVariety":["Connecticut","Shade"],"fillerOrigin":["Dominikanische Republik","Mexiko"],"binderOrigin":["Mexiko"],"aromaProfileManufacturer":["Blumig","Kaffee","Schokolade","Zedernholz"],"strength":"Medium","smokingDuration":"45 bis 90 Min","price":13}
