{"name":"Rocky Patel The Edge Corojo Robusto","url":"https://www.noblego.de/rocky-patel-the-edge-corojo-robusto/","brand":"Rocky Patel","series":"The Edge","details":{"Fazit":"Die Rocky Patel The Edge Corojo Robusto ist eine große Zigarre für den besonders intensiven Tabakgenuss. Ganz besonders empfohlen sei die rustikal gestylte Holzkiste mit zwanzig Stück dieser edlen Longfiller, die sich natürlich ganz hervorragend als Geschenk eignet.","Genuss":"Die Rocky Patel The Edge Corojo Robusto ist im Durchmesser eine Robusto, bei der Länge hat Mister Patel noch etliche Millimeter drauf gelegt. Das ebenmäßige, hellbraune Deckblatt ist, wie der Name bereits verrät, ein Corojo aus Honduras. Das Innenleben aus honduranischen und nicaraguanischen Tabaken gibt diesem edlen Longfiller eine beachtliche Stärke, die ihn eher für erfahrene Aficionados geeignet erscheinen lässt. Mit einer Länge von 14 cm und einem Durchmesser von 19,8 mm handelt es sich um ein Robusto Extra Format, das auch eine dementsprechende Rauchdauer von rund einer Stunde bietet.  Vollgepackt mit Aromen von Holz, Leder, Espresso, Pfeffer und etwas Süße bietet die Rocky Patel The Edge Corojo Robusto ein sehr nachhaltiges Raucherlebnis.","Hintergrund":"Die Rocky Patel The Edge Corojo Gordo entstand in Zusammenarbeit mit dem berühmten Nestor Plasencia, einem der ganz großen Tabakhersteller in Mittelamerika. Die Verwendung lange gereifter, edelster Tabake und die dezente Binde am unteren Ende sind Markenzeichen dieser tollen Zigarren. Die gesamte Serie gilt als kräftig, würzig und sehr gelungen. In den Vereinigten Staaten hat sie längst Berühmtheit erlangt. Sie ist nun auch bei uns erhältlich. Im Jahr 2014 wurden diese Zigarren mit der \u003cem\u003eCigar Trophy\u003c/em\u003e als beste honduranische Zigarre ausgezeichnet und 2015 erhielt sie im Tasting des \u003cem\u003eCigar Aficionado\u003c/em\u003e stolze 90 Punkte."},"diameter_mm":19.8,"ring":50,"length_mm":140,"length_inch":0,"format":"Robusto","maker":"Rocky Patel","manufactureOrigin":"Honduras","construction":"Longfiller","isBoxpressed":false,"wrapperOrigin":["Honduras"],"wrapperTobaccoVariety":["Corojo"],"fillerOrigin":["Honduras","Nicaragua"],"binderOrigin":["Nicaragua"],"aromaProfileManufacturer":["Holz","Kaffee","Leder","Pfeffer","Süß"],"strength":"Stark","flavourStrength":"Medium-kräftig","smokingDuration":"45 bis 90 Min","price":7.7}
