{"name":"My Father The Judge Toro","url":"https://www.noblego.de/my-father-the-judge-toro/","brand":"My Father","series":"My Father The Judge","details":{"Fazit":"Vollmundiger Premiumgenuss für den Gaumen! Die My Father The Judge Toro aus Nicaragua wird Ihnen einige sehr genussvolle Momente bescheren.","Genuss":"Wundervoll verarbeitet und mit einem feinen Sumatra Deckblatt aus Ecuador ummantelt, bietet die My Father The Judge Toro einen imposanten Anblick. Darunter ist die Premium Longfiller mit einem doppelten Umblatt versehen worden, dabei handelt es sich um nicaraguanischen Criollo und Corojo Tabak. Die lang gereiften Tabake der Einlage stammen ebenfalls aus Nicaragua. Im cremigen Rauchverlauf kann der Genießer sich auf einige vollmundige Aromen freuen, die in erster Linie von Holz, Mandel, Kaffee, Nuss und Anis geprägt sind. Stimmig begleitet wird diese interessante Komposition von leicht salzigen Tönen und einer angenehmen Säure, die dem gesamten Geschmacksbild der My Father The Judge Toro einen angenehm runden Charakter verleihen.","Hintergrund":"Mit der The Judge Serie zeigt man bei My Father Cigars eindrucksvoll, wie man mit erlesenen Tabaken umgeht, um daraus wunderschöne und schmackhafte Premiumzigarren zu fertigen. Schließlich wurde die The Judge Grand Robusto der spannenden Auflage nicht umsonst von der strengen Jury des Cigar Journals zur Zigarre des Jahres 2017 gewählt."},"diameter_mm":22,"ring":56,"length_mm":152,"length_inch":0,"format":"Toro","maker":"Jose Pepin Garcia","manufactureOrigin":"Nicaragua","construction":"Longfiller","isBoxpressed":true,"wrapperOrigin":["Ecuador"],"wrapperTobaccoVariety":["Sumatra"],"fillerOrigin":["Nicaragua"],"binderOrigin":["Nicaragua"],"aromaProfileManufacturer":["Anis","Brioche","Cremig","Holz","Kaffee","Mandel","Nuss"],"strength":"Medium","flavourStrength":"Kräftig","smokingDuration":"45 bis 90 Min","price":18.2}
