{"name":"Epic La Rubia Churchill ","url":"https://www.noblego.de/epic-la-rubia-churchill-zigarren/","brand":"Epic","series":"Rubia","details":{"Genussverlauf":"Mit einem hellbraunen Connecticut Deckblatt aus Ecuador, einer dominikanisch-nicaraguanischen Einlage und einem Umblatt aus Mexiko ausgestattet, sorgt die La Rubia Churchill der dominikanischen Marke Epic für einen herrlich sanften Vortrag am Gaumen. Es sind feine Holz-, Leder- und Nussaromen, die von einer zarten Süße, floralen Noten sowie einer sehr gefälligen Würze begleitet, den geschmacklichen Rahmen füllen. Gut 90 Minuten lässt sich das 17,7 cm lange Format Zeit, seinen cremigen Charme zu versprühen. Ihr etwas zu leichtes Zugverhalten macht sie durch ihren wunderbar voluminösen Rauch wieder wett. Beim Abbrand zeigten unsere Probeexemplare keinerlei Schwächen.","Resümee":"Die Epic La Rubia Churchill fällt in die inoffizielle Kategorie der Frühstückszigarren. Diese Art Zigarren sind extrem unaufdringlich und mild im Abgang, sodass man sie bereits am frühen Morgen auf nüchternen Magen genießen könnte. Daher gilt sie ebenfalls als absolut einsteigerfreundlicher Smoke, der interessierten Zigarrenfreunden einiges zu bieten hat."},"diameter_mm":19.8,"ring":50,"length_mm":177,"length_inch":0,"format":"Churchill","manufactureOrigin":"Dominikanische Republik","construction":"Longfiller","isBoxpressed":false,"wrapperOrigin":["Ecuador"],"wrapperTobaccoVariety":["Connecticut"],"fillerOrigin":["Dominikanische Republik","Nicaragua"],"binderOrigin":["Mexiko"],"aromaProfileManufacturer":["Cremig","Floral","Holz","Leder","Nuss","Süß"],"flavourStrength":"Mild-aromatisch","smokingDuration":"60 bis 90 Min","price":8.1}
