{"name":"Plasencia Alma Fuerte Generation V Salomon","url":"https://www.noblego.de/plasencia-alma-fuerte-generation-v-salomon/","brand":"Plasencia","series":"Alma Fuerte","details":{"Fazit":"Mit der Plasencia Alma Fuerte Generation V Salomon 7x58 haben Nestor Plasencia und seinem Team eine spannende Premium-Zigarre kreiert. Diese Puro aus Nicaragua verdient das Prädikat „besonders gelungen“ und wir wünschen viel Spaß beim Smoke. Gern in Begleitung eines süßen Cocktails oder eines fruchtigen Weißweins.","Genuss":"Genuss beginnt hier schon bei der Präsentation. Die Plasencia Alma Fuerte Generation V Salomon 7x58 macht schon in der mattschwarzen Holzkiste, die je zehn Zigarren enthält, einen erlesenen Eindruck. Mit ihren goldenen Banderolen und dem dunklen, seidig-schimmernden Jalapa-Deckblatt aus Nicaragua ist diese Puro eine echte Augenweide. Und auch der einem entgegenströmende Kaltgeruch macht einiges her und vor allem Vorfreude auf den folgenden Smoke. Bei einem 58er Ringmaß und einer Länge von 7 Inch (beziehungsweise von 178 Millimetern) darf sich der geneigte Genussraucher auf einen langwährenden Smoke freuen. Wer sich Zeit lässt und geduldig nur gelegentlich an der Salomones zieht darf bis zu 90 Minuten lang eine starke Puro aus Nicaragua genießen. Dabei präsentiert diese sehr würzige und kräftige Zigarre einen vollmundigen, schweren Rauch. Aromen von Zedernholz und Erde sind allzeit präsent, immer wieder mit eingestreuten Pfeffernoten. Im letzten Drittel scheinen verstärkt nussige Anklänge von gerösteten Pecanüssen auf, hinzu gesellen sich dunkle Kakaonoten. Der Abbrand und das Zugverhalten sind einwandfrei, was aber bei dieser guten Verarbeitung auch nicht weiter verwunderlich ist.","Hintergrund":"Klar, der Preis bei dieser Salomones ist schon ein stolzer. Wenn man sich diese Vitola jedoch einmal genauer anschaut, so wird schnell klar, dass sie dies auch wert ist. So sollen die Tabake, die für den Blend verwendet wurden, aus den besten Lagerbeständen der Plasencia-Familie stammen und extra lang gereift sein."},"diameter_mm":23,"ring":58,"length_mm":178,"length_inch":0,"format":"Salomones","maker":"Nestor Plasencia","manufactureOrigin":"Nicaragua","construction":"Longfiller","isBoxpressed":true,"wrapperOrigin":["Nicaragua"],"wrapperTobaccoVariety":["Jalapa"],"fillerOrigin":["Nicaragua"],"binderOrigin":["Nicaragua"],"aromaProfileManufacturer":["Cremig","Erdig","Nuss","Pfeffer","Würzig","Zedernholz"],"strength":"Stark","flavourStrength":"Medium-kräftig","smokingDuration":"90 Min oder länger","price":27}
