{"name":"Condega Serie S Masaya Limitada Robusto","url":"https://www.noblego.de/condega-serie-s-masaya-limitada-robusto-zigarren/","brand":"Condega","series":"Serie S Masaya","details":{"Genussverlauf":"Alle Tabake der Condega Serie S Masaya Limitada Robusto stammen aus Nicaragua und haben eine Mindestreifezeit von drei Jahren vorzuweisen. Ihr Deckblatt ist ein sattbraunes Sun Grown der Sorte Corojo. In ihrer Einlage und als Umblatt lassen sich ebenfalls Corojo Tabake vorfinden. Den Rest der Einlage dieser sehr delikaten Longfiller-Kreation bilden handverlesene Criollo 98 Tabake. Ein nur kurz anhaltender Pfefferkick zu Beginn bereitet den Gaumen des Genießers auf einen herrlich komplexen Aromaverlauf vor. Dieser wird bestimmt von einer delikaten Melange aus cremig unterlegten Noten verschiedener Gewürze, Nuss, Holz, Schokolade und Erde. Unter diese mischt sich eine subtile Süße, die zunächst einen malzigen Charakter besitzt und im späteren Verlauf eine interessante Wandlung erfährt. Die sehr gute Verarbeitung der Robusto spiegelt sich durch ein nahezu perfektes Zug- und Abbrandverhalten wider.","Nice to know":"Am Kopf aller Condega Serie S Masaya Limitada Zigarren wurde ein sogenannter Pigtail angebracht, der den Genuss ohne Anschneiden ermöglicht. Zudem hat man es hier mit „Closed Foot“ Zigarren zu tun, bei denen das Deckblatt ein wenig übersteht, was die Brandannahme erheblich begünstigt.","Resümee":"Die Condega Serie S Masaya Limitada Robusto offeriert würzig-süßen und cremigen Zigarrengenuss zu einem hervorragenden Preis-Leistungs-Verhältnis. Leider ist sie nur in einer kleinen, limitierten Auflage erschienen und daher nur solange der Vorrat reicht, verfügbar."},"diameter_mm":0,"ring":52,"length_mm":127,"length_inch":0,"format":"Robusto","manufactureOrigin":"Nicaragua","construction":"Longfiller","isBoxpressed":false,"wrapperOrigin":["Nicaragua"],"wrapperTobaccoVariety":["Corojo"],"fillerOrigin":["Nicaragua"],"binderOrigin":["Nicaragua"],"aromaProfileManufacturer":["Erdig","Gewürze","Holz","Malz","Nuss","Pfeffer","Schokolade","Süß"],"strength":"Medium","flavourStrength":"Medium-aromatisch","smokingDuration":"45 bis 90 Min","price":5.9,"additionalNotes":"Limited"}
