{"name":"Quisqueya Maduro Torpedo","url":"https://www.noblego.de/quisqueya-maduro-torpedo/","brand":"Quisqueya","series":"Maduro","details":{"Fazit":"Die Quisqueya Maduro Torpedo ist eine sehr preiswerte und aromatische Bundle-Zigarre, die zu jeder Tageszeit und zu jedem Anlass Freude bereitet. Perfekt wird der Genuss zu einer Tasse Kaffee mit einem Stück Zartbitterschokolade oder einer Heißen Schokolade.","Genuss":"Die milde und medium-aromatische Quisqueya Maduro im Torpedo-Format vereint mehrere Aromen miteinander. Zu Beginn zeigt sich ein sehr mild-cremiger Geschmack mit einem angenehmen Aroma von Kaffee. Im weiteren Rauchverlauf zeigt sich eine leichte Süße mit Untertönen von Kakao und Zartbitterschokolade. Zum Ende hin entwickelt sich eine dezente Schärfe, die jedoch keineswegs zu scharf wird. Das sehr schöne dunkle Connecticut Broadleaf Maduro Deckblatt umschließt Tabake aus der Dominikanischen Republik und Nicaragua. Das Umblatt stammt aus Indonesien. Diese Bundle-Zigarre misst neben einem Durchmesser von 20 Millimetern eine Länge von knapp 16 Zentimetern. Die Rauchdauer beträgt rund 60 Minuten."},"diameter_mm":20,"ring":50,"length_mm":157,"length_inch":0,"format":"Torpedo","manufactureOrigin":"Dominikanische Republik","construction":"Mediumfiller","isBoxpressed":false,"wrapperOrigin":["Connecticut River Valley"],"wrapperTobaccoVariety":["Connecticut","Broadleaf","Maduro"],"fillerOrigin":["Dominikanische Republik","Nicaragua"],"binderOrigin":["Indonesien"],"aromaProfileManufacturer":["Cremig","Kaffee","Süß","Zartbitter"],"strength":"Mild","flavourStrength":"Medium-aromatisch","smokingDuration":"45 bis 90 Min","price":4.1}
