{"name":"Placeres Toro","url":"https://www.noblego.de/placeres-toro/","brand":"Placeres","series":"","details":{"Fazit":"Ein Mediumfiller, der sich sehen und vor allem schmecken lassen kann. Die Placeres Toro atmet die langjährige Erfahrung und Liebe zum Tabak eines Nestor Plasencia. Probieren lohnt sich!","Genuss":"Sicherlich kann man an einen Mediumfiller nicht die Anforderungen stellen, den ein hochwertiger Longfiller zu genügen hat. Aber die Placeres Toro schlägt sich sehr wacker, zumal sie ebenso von Hand gefertigt wird wie die Longfiller-Serien aus dem Hause Plasencia. Zug und Abbrand gestalten sich nahezu ideal und lassen den Rauch wunderbar zirkulieren. Mit klassischen Maßen von 152 mm Länge und 20,6 mm Durchmesser präsentiert sich hier eine klassische Toro, die eine gute Stunde Verweildauer zulässt. Der Blend ist eine Zusammenstellung aus honduranischen und nicaraguanischen Tabaken in der Einlage, einem honduranischen Umblatt und einem Connecticut Seed Deckblatt ebenfalls aus Honduras. Aromatisch werden Sie beim Smoke Noten von Gras, Holz, Kaffee und Schokolade erschmecken. Alles in allem ein gelungenes Stück Rauchgenuss.","Hintergrund":"Der günstige Preis der Placeres Toro liegt zum einen an ihrer Anlage als Mediumfiller, aber auch ihre Verpackung als Bundle spielt dabei eine Rolle. Es handelt sich hier jedoch nicht um ein gewöhnliches Bundle, denn die 25 „zusammengebundenen“ Zigarren werden in einer stilvoll gestalteten Metallkiste geliefert, die mit einem innenliegenden Schwammbefeuchter sogar wie ein kleiner Humidor funktioniert."},"diameter_mm":20.6,"ring":52,"length_mm":152,"length_inch":0,"format":"Toro","maker":"Nestor Plasencia","manufactureOrigin":"Honduras","construction":"Mediumfiller","isBoxpressed":false,"wrapperOrigin":["Honduras"],"wrapperTobaccoVariety":["Connecticut","Seed"],"fillerOrigin":["Honduras","Nicaragua"],"binderOrigin":["Honduras"],"aromaProfileManufacturer":["Gras","Holz","Kaffee","Schokolade"],"strength":"Medium","flavourStrength":"Medium-aromatisch","smokingDuration":"45 bis 90 Min","price":2.6}
